{
  "metadata": {
    "city": "上饶市",
    "state": "JX",
    "country": "CHN",
    "wmo": "586260",
    "lat": 28.455,
    "lon": 117.943,
    "tz": 8.0,
    "elev": 90.0,
    "city_short_zh": "上饶",
    "city_en": "Shangrao",
    "province": "江西省",
    "province_en": "Jiangxi",
    "admin_level": "地级市",
    "catalog_id": "prefecture-shangrao",
    "prefecture_index": 130,
    "division_code": "361100",
    "source_station_city": "Shangrao",
    "source_station_wmo": "586260",
    "source_station_lat": 28.483,
    "source_station_lon": 117.983,
    "station_match_quality": "direct",
    "catalog_type": "prefecture_level_admin_unit"
  },
  "yearly": {
    "avg_temp": 18.1,
    "total_precip": 1648.4,
    "avg_humidity": 75.98,
    "avg_wind": 2.06,
    "total_solar": 1429.02,
    "avg_cloud": 62.1,
    "avg_opaque_cloud": 67.9,
    "avg_visibility": 7.2,
    "avg_apparent_temp": 18.56,
    "avg_dew_point": 13.39,
    "growing_season": 344,
    "water_temp": 19.6,
    "solar_energy": 214.35,
    "data_source": "OneBuilding Climate.OneBuilding.org EPW / TMYx-CSWD processed locally",
    "method_note": "Monthly high/low are mean daily high/low; precipitation probability is wet days (>=1 mm/day); tourism score uses climate-comfort 8:00-21:00 hourly apparent-temperature, cloud, and precipitation component scores.",
    "tourism_score_avg": 5.6,
    "beach_score_avg": 5.1,
    "best_tourism_months": "4-5月、9-11月",
    "best_time": "4-5月、9-11月",
    "tourism_peak_month": 10,
    "overview": "温带气候，四季分明。 降水极丰沛。",
    "admin_level": "地级市",
    "prefecture_index": 130,
    "division_code": "361100",
    "source_station_id": "586260",
    "source_station_name": "Shangrao",
    "station_match_quality": "direct",
    "catalog_type": "prefecture_level_admin_unit"
  },
  "monthly": {
    "1": {
      "temp_avg": 6.41,
      "temp_max": 10.51,
      "temp_min": 2.65,
      "apparent_temp_avg": 5.37,
      "dew_point_avg": 2.63,
      "humidity": 78.44,
      "wind": 1.94,
      "wind_dir": 1.2,
      "wind_dir_text": "北",
      "precip": 85.1,
      "precip_days": 16,
      "precip_probability": 51.6,
      "solar": 79510.0,
      "cloud": 62.7,
      "opaque_cloud": 71.5,
      "visibility": 7.3,
      "sunny_rate": 28.5,
      "cloud_score": 4.7,
      "precip_score": 8.7,
      "tourism_temp_score": 0.9,
      "tourism_score": 3.8,
      "beach_score": 3.3,
      "comfort_label": "偏不舒适",
      "cloud_categories": {
        "clear": {
          "label": "晴天",
          "pct": 20.7
        },
        "mostly_clear": {
          "label": "大部分晴天",
          "pct": 4.8
        },
        "partly_cloudy": {
          "label": "部分多云",
          "pct": 9.4
        },
        "mostly_cloudy": {
          "label": "大部分多云",
          "pct": 13.4
        },
        "overcast": {
          "label": "阴天",
          "pct": 51.6
        }
      },
      "humidity_comfort": {
        "dry": {
          "label": "干燥",
          "pct": 98.7
        },
        "comfortable": {
          "label": "舒适",
          "pct": 1.3
        },
        "humid": {
          "label": "潮湿",
          "pct": 0.0
        },
        "muggy": {
          "label": "闷热",
          "pct": 0.0
        },
        "oppressive": {
          "label": "闷热难受",
          "pct": 0.0
        },
        "miserable": {
          "label": "极为难受",
          "pct": 0.0
        }
      }
    },
    "2": {
      "temp_avg": 7.78,
      "temp_max": 11.95,
      "temp_min": 4.11,
      "apparent_temp_avg": 6.87,
      "dew_point_avg": 3.06,
      "humidity": 74.54,
      "wind": 1.81,
      "wind_dir": 37.2,
      "wind_dir_text": "东北",
      "precip": 117.1,
      "precip_days": 13,
      "precip_probability": 46.4,
      "solar": 85308.0,
      "cloud": 62.6,
      "opaque_cloud": 65.5,
      "visibility": 0.8,
      "sunny_rate": 34.5,
      "cloud_score": 5.5,
      "precip_score": 8.2,
      "tourism_temp_score": 1.6,
      "tourism_score": 4.2,
      "beach_score": 3.5,
      "comfort_label": "偏不舒适",
      "cloud_categories": {
        "clear": {
          "label": "晴天",
          "pct": 11.8
        },
        "mostly_clear": {
          "label": "大部分晴天",
          "pct": 9.2
        },
        "partly_cloudy": {
          "label": "部分多云",
          "pct": 16.5
        },
        "mostly_cloudy": {
          "label": "大部分多云",
          "pct": 17.9
        },
        "overcast": {
          "label": "阴天",
          "pct": 44.6
        }
      },
      "humidity_comfort": {
        "dry": {
          "label": "干燥",
          "pct": 99.3
        },
        "comfortable": {
          "label": "舒适",
          "pct": 0.7
        },
        "humid": {
          "label": "潮湿",
          "pct": 0.0
        },
        "muggy": {
          "label": "闷热",
          "pct": 0.0
        },
        "oppressive": {
          "label": "闷热难受",
          "pct": 0.0
        },
        "miserable": {
          "label": "极为难受",
          "pct": 0.0
        }
      }
    },
    "3": {
      "temp_avg": 11.69,
      "temp_max": 15.17,
      "temp_min": 8.37,
      "apparent_temp_avg": 11.23,
      "dew_point_avg": 8.3,
      "humidity": 81.03,
      "wind": 2.13,
      "wind_dir": 45.6,
      "wind_dir_text": "东北",
      "precip": 213.8,
      "precip_days": 21,
      "precip_probability": 67.7,
      "solar": 89560.0,
      "cloud": 75.6,
      "opaque_cloud": 77.5,
      "visibility": 8.2,
      "sunny_rate": 22.5,
      "cloud_score": 3.8,
      "precip_score": 7.7,
      "tourism_temp_score": 3.5,
      "tourism_score": 4.6,
      "beach_score": 3.2,
      "comfort_label": "可接受",
      "cloud_categories": {
        "clear": {
          "label": "晴天",
          "pct": 6.6
        },
        "mostly_clear": {
          "label": "大部分晴天",
          "pct": 3.8
        },
        "partly_cloudy": {
          "label": "部分多云",
          "pct": 8.2
        },
        "mostly_cloudy": {
          "label": "大部分多云",
          "pct": 20.3
        },
        "overcast": {
          "label": "阴天",
          "pct": 61.2
        }
      },
      "humidity_comfort": {
        "dry": {
          "label": "干燥",
          "pct": 81.9
        },
        "comfortable": {
          "label": "舒适",
          "pct": 11.3
        },
        "humid": {
          "label": "潮湿",
          "pct": 4.4
        },
        "muggy": {
          "label": "闷热",
          "pct": 2.3
        },
        "oppressive": {
          "label": "闷热难受",
          "pct": 0.1
        },
        "miserable": {
          "label": "极为难受",
          "pct": 0.0
        }
      }
    },
    "4": {
      "temp_avg": 17.68,
      "temp_max": 21.44,
      "temp_min": 13.12,
      "apparent_temp_avg": 17.66,
      "dew_point_avg": 13.62,
      "humidity": 78.74,
      "wind": 2.27,
      "wind_dir": 52.5,
      "wind_dir_text": "东北",
      "precip": 198.8,
      "precip_days": 20,
      "precip_probability": 66.7,
      "solar": 121149.0,
      "cloud": 68.5,
      "opaque_cloud": 73.6,
      "visibility": 8.5,
      "sunny_rate": 26.4,
      "cloud_score": 4.3,
      "precip_score": 7.9,
      "tourism_temp_score": 7.3,
      "tourism_score": 6.7,
      "beach_score": 4.6,
      "comfort_label": "舒适",
      "cloud_categories": {
        "clear": {
          "label": "晴天",
          "pct": 12.4
        },
        "mostly_clear": {
          "label": "大部分晴天",
          "pct": 4.3
        },
        "partly_cloudy": {
          "label": "部分多云",
          "pct": 12.5
        },
        "mostly_cloudy": {
          "label": "大部分多云",
          "pct": 15.8
        },
        "overcast": {
          "label": "阴天",
          "pct": 55.0
        }
      },
      "humidity_comfort": {
        "dry": {
          "label": "干燥",
          "pct": 35.8
        },
        "comfortable": {
          "label": "舒适",
          "pct": 32.9
        },
        "humid": {
          "label": "潮湿",
          "pct": 16.2
        },
        "muggy": {
          "label": "闷热",
          "pct": 14.4
        },
        "oppressive": {
          "label": "闷热难受",
          "pct": 0.6
        },
        "miserable": {
          "label": "极为难受",
          "pct": 0.0
        }
      }
    },
    "5": {
      "temp_avg": 22.24,
      "temp_max": 26.25,
      "temp_min": 18.64,
      "apparent_temp_avg": 22.58,
      "dew_point_avg": 18.06,
      "humidity": 78.79,
      "wind": 2.05,
      "wind_dir": 52.7,
      "wind_dir_text": "东北",
      "precip": 249.3,
      "precip_days": 19,
      "precip_probability": 61.3,
      "solar": 132195.0,
      "cloud": 71.8,
      "opaque_cloud": 73.3,
      "visibility": 7.7,
      "sunny_rate": 26.7,
      "cloud_score": 4.6,
      "precip_score": 7.9,
      "tourism_temp_score": 8.1,
      "tourism_score": 7.2,
      "beach_score": 6.4,
      "comfort_label": "舒适",
      "cloud_categories": {
        "clear": {
          "label": "晴天",
          "pct": 5.1
        },
        "mostly_clear": {
          "label": "大部分晴天",
          "pct": 4.6
        },
        "partly_cloudy": {
          "label": "部分多云",
          "pct": 15.2
        },
        "mostly_cloudy": {
          "label": "大部分多云",
          "pct": 20.3
        },
        "overcast": {
          "label": "阴天",
          "pct": 54.8
        }
      },
      "humidity_comfort": {
        "dry": {
          "label": "干燥",
          "pct": 7.4
        },
        "comfortable": {
          "label": "舒适",
          "pct": 16.9
        },
        "humid": {
          "label": "潮湿",
          "pct": 19.9
        },
        "muggy": {
          "label": "闷热",
          "pct": 34.1
        },
        "oppressive": {
          "label": "闷热难受",
          "pct": 19.6
        },
        "miserable": {
          "label": "极为难受",
          "pct": 2.0
        }
      }
    },
    "6": {
      "temp_avg": 25.71,
      "temp_max": 30.04,
      "temp_min": 21.99,
      "apparent_temp_avg": 26.97,
      "dew_point_avg": 21.45,
      "humidity": 79.18,
      "wind": 2.24,
      "wind_dir": 69.0,
      "wind_dir_text": "东北偏东",
      "precip": 345.1,
      "precip_days": 16,
      "precip_probability": 53.3,
      "solar": 137497.0,
      "cloud": 72.9,
      "opaque_cloud": 75.0,
      "visibility": 7.0,
      "sunny_rate": 25.0,
      "cloud_score": 4.4,
      "precip_score": 7.2,
      "tourism_temp_score": 5.7,
      "tourism_score": 5.7,
      "beach_score": 6.4,
      "comfort_label": "可接受",
      "cloud_categories": {
        "clear": {
          "label": "晴天",
          "pct": 6.5
        },
        "mostly_clear": {
          "label": "大部分晴天",
          "pct": 6.2
        },
        "partly_cloudy": {
          "label": "部分多云",
          "pct": 10.4
        },
        "mostly_cloudy": {
          "label": "大部分多云",
          "pct": 17.8
        },
        "overcast": {
          "label": "阴天",
          "pct": 59.0
        }
      },
      "humidity_comfort": {
        "dry": {
          "label": "干燥",
          "pct": 0.6
        },
        "comfortable": {
          "label": "舒适",
          "pct": 0.7
        },
        "humid": {
          "label": "潮湿",
          "pct": 5.1
        },
        "muggy": {
          "label": "闷热",
          "pct": 34.0
        },
        "oppressive": {
          "label": "闷热难受",
          "pct": 39.6
        },
        "miserable": {
          "label": "极为难受",
          "pct": 20.0
        }
      }
    },
    "7": {
      "temp_avg": 29.17,
      "temp_max": 34.14,
      "temp_min": 25.23,
      "apparent_temp_avg": 32.58,
      "dew_point_avg": 23.7,
      "humidity": 74.27,
      "wind": 1.58,
      "wind_dir": 130.9,
      "wind_dir_text": "东南",
      "precip": 146.6,
      "precip_days": 13,
      "precip_probability": 41.9,
      "solar": 175114.0,
      "cloud": 62.0,
      "opaque_cloud": 64.8,
      "visibility": 5.8,
      "sunny_rate": 35.2,
      "cloud_score": 5.7,
      "precip_score": 8.0,
      "tourism_temp_score": 2.0,
      "tourism_score": 4.4,
      "beach_score": 5.5,
      "comfort_label": "偏不舒适",
      "cloud_categories": {
        "clear": {
          "label": "晴天",
          "pct": 11.6
        },
        "mostly_clear": {
          "label": "大部分晴天",
          "pct": 10.2
        },
        "partly_cloudy": {
          "label": "部分多云",
          "pct": 14.5
        },
        "mostly_cloudy": {
          "label": "大部分多云",
          "pct": 21.2
        },
        "overcast": {
          "label": "阴天",
          "pct": 42.5
        }
      },
      "humidity_comfort": {
        "dry": {
          "label": "干燥",
          "pct": 0.0
        },
        "comfortable": {
          "label": "舒适",
          "pct": 0.0
        },
        "humid": {
          "label": "潮湿",
          "pct": 0.0
        },
        "muggy": {
          "label": "闷热",
          "pct": 2.0
        },
        "oppressive": {
          "label": "闷热难受",
          "pct": 51.1
        },
        "miserable": {
          "label": "极为难受",
          "pct": 46.9
        }
      }
    },
    "8": {
      "temp_avg": 29.03,
      "temp_max": 33.42,
      "temp_min": 25.33,
      "apparent_temp_avg": 31.75,
      "dew_point_avg": 22.5,
      "humidity": 69.58,
      "wind": 2.02,
      "wind_dir": 74.1,
      "wind_dir_text": "东北偏东",
      "precip": 102.9,
      "precip_days": 13,
      "precip_probability": 41.9,
      "solar": 175267.0,
      "cloud": 52.8,
      "opaque_cloud": 56.2,
      "visibility": 8.0,
      "sunny_rate": 43.8,
      "cloud_score": 6.5,
      "precip_score": 8.9,
      "tourism_temp_score": 2.0,
      "tourism_score": 4.8,
      "beach_score": 6.6,
      "comfort_label": "可接受",
      "cloud_categories": {
        "clear": {
          "label": "晴天",
          "pct": 14.2
        },
        "mostly_clear": {
          "label": "大部分晴天",
          "pct": 15.1
        },
        "partly_cloudy": {
          "label": "部分多云",
          "pct": 19.2
        },
        "mostly_cloudy": {
          "label": "大部分多云",
          "pct": 25.9
        },
        "overcast": {
          "label": "阴天",
          "pct": 25.5
        }
      },
      "humidity_comfort": {
        "dry": {
          "label": "干燥",
          "pct": 0.0
        },
        "comfortable": {
          "label": "舒适",
          "pct": 1.7
        },
        "humid": {
          "label": "潮湿",
          "pct": 3.9
        },
        "muggy": {
          "label": "闷热",
          "pct": 11.0
        },
        "oppressive": {
          "label": "闷热难受",
          "pct": 60.2
        },
        "miserable": {
          "label": "极为难受",
          "pct": 23.1
        }
      }
    },
    "9": {
      "temp_avg": 24.93,
      "temp_max": 29.08,
      "temp_min": 21.39,
      "apparent_temp_avg": 25.94,
      "dew_point_avg": 19.99,
      "humidity": 75.88,
      "wind": 2.2,
      "wind_dir": 52.1,
      "wind_dir_text": "东北",
      "precip": 80.6,
      "precip_days": 13,
      "precip_probability": 43.3,
      "solar": 133766.0,
      "cloud": 65.0,
      "opaque_cloud": 67.5,
      "visibility": 8.0,
      "sunny_rate": 32.5,
      "cloud_score": 5.4,
      "precip_score": 8.6,
      "tourism_temp_score": 6.1,
      "tourism_score": 6.6,
      "beach_score": 7.0,
      "comfort_label": "舒适",
      "cloud_categories": {
        "clear": {
          "label": "晴天",
          "pct": 9.4
        },
        "mostly_clear": {
          "label": "大部分晴天",
          "pct": 11.2
        },
        "partly_cloudy": {
          "label": "部分多云",
          "pct": 11.8
        },
        "mostly_cloudy": {
          "label": "大部分多云",
          "pct": 20.0
        },
        "overcast": {
          "label": "阴天",
          "pct": 47.5
        }
      },
      "humidity_comfort": {
        "dry": {
          "label": "干燥",
          "pct": 9.0
        },
        "comfortable": {
          "label": "舒适",
          "pct": 6.9
        },
        "humid": {
          "label": "潮湿",
          "pct": 6.0
        },
        "muggy": {
          "label": "闷热",
          "pct": 22.1
        },
        "oppressive": {
          "label": "闷热难受",
          "pct": 47.9
        },
        "miserable": {
          "label": "极为难受",
          "pct": 8.1
        }
      }
    },
    "10": {
      "temp_avg": 19.63,
      "temp_max": 24.67,
      "temp_min": 15.44,
      "apparent_temp_avg": 19.61,
      "dew_point_avg": 12.91,
      "humidity": 67.45,
      "wind": 2.81,
      "wind_dir": 47.7,
      "wind_dir_text": "东北",
      "precip": 29.8,
      "precip_days": 7,
      "precip_probability": 22.6,
      "solar": 121160.0,
      "cloud": 50.6,
      "opaque_cloud": 55.0,
      "visibility": 8.3,
      "sunny_rate": 45.0,
      "cloud_score": 6.6,
      "precip_score": 9.4,
      "tourism_temp_score": 8.1,
      "tourism_score": 8.1,
      "beach_score": 6.6,
      "comfort_label": "最佳",
      "cloud_categories": {
        "clear": {
          "label": "晴天",
          "pct": 21.2
        },
        "mostly_clear": {
          "label": "大部分晴天",
          "pct": 11.6
        },
        "partly_cloudy": {
          "label": "部分多云",
          "pct": 18.1
        },
        "mostly_cloudy": {
          "label": "大部分多云",
          "pct": 22.4
        },
        "overcast": {
          "label": "阴天",
          "pct": 26.6
        }
      },
      "humidity_comfort": {
        "dry": {
          "label": "干燥",
          "pct": 39.0
        },
        "comfortable": {
          "label": "舒适",
          "pct": 28.5
        },
        "humid": {
          "label": "潮湿",
          "pct": 15.9
        },
        "muggy": {
          "label": "闷热",
          "pct": 16.4
        },
        "oppressive": {
          "label": "闷热难受",
          "pct": 0.3
        },
        "miserable": {
          "label": "极为难受",
          "pct": 0.0
        }
      }
    },
    "11": {
      "temp_avg": 13.87,
      "temp_max": 18.73,
      "temp_min": 10.25,
      "apparent_temp_avg": 13.67,
      "dew_point_avg": 9.35,
      "humidity": 75.43,
      "wind": 1.73,
      "wind_dir": 33.1,
      "wind_dir_text": "东北偏北",
      "precip": 38.9,
      "precip_days": 8,
      "precip_probability": 26.7,
      "solar": 91316.0,
      "cloud": 52.9,
      "opaque_cloud": 66.2,
      "visibility": 8.6,
      "sunny_rate": 33.8,
      "cloud_score": 5.6,
      "precip_score": 9.5,
      "tourism_temp_score": 5.7,
      "tourism_score": 6.6,
      "beach_score": 4.3,
      "comfort_label": "舒适",
      "cloud_categories": {
        "clear": {
          "label": "晴天",
          "pct": 23.5
        },
        "mostly_clear": {
          "label": "大部分晴天",
          "pct": 7.4
        },
        "partly_cloudy": {
          "label": "部分多云",
          "pct": 15.1
        },
        "mostly_cloudy": {
          "label": "大部分多云",
          "pct": 22.4
        },
        "overcast": {
          "label": "阴天",
          "pct": 31.7
        }
      },
      "humidity_comfort": {
        "dry": {
          "label": "干燥",
          "pct": 78.3
        },
        "comfortable": {
          "label": "舒适",
          "pct": 17.6
        },
        "humid": {
          "label": "潮湿",
          "pct": 4.0
        },
        "muggy": {
          "label": "闷热",
          "pct": 0.0
        },
        "oppressive": {
          "label": "闷热难受",
          "pct": 0.0
        },
        "miserable": {
          "label": "极为难受",
          "pct": 0.0
        }
      }
    },
    "12": {
      "temp_avg": 8.4,
      "temp_max": 13.73,
      "temp_min": 4.16,
      "apparent_temp_avg": 7.7,
      "dew_point_avg": 4.49,
      "humidity": 78.47,
      "wind": 1.95,
      "wind_dir": 21.6,
      "wind_dir_text": "东北偏北",
      "precip": 40.4,
      "precip_days": 8,
      "precip_probability": 25.8,
      "solar": 87182.0,
      "cloud": 47.7,
      "opaque_cloud": 69.1,
      "visibility": 7.8,
      "sunny_rate": 30.9,
      "cloud_score": 5.2,
      "precip_score": 9.4,
      "tourism_temp_score": 1.9,
      "tourism_score": 4.6,
      "beach_score": 3.7,
      "comfort_label": "可接受",
      "cloud_categories": {
        "clear": {
          "label": "晴天",
          "pct": 38.0
        },
        "mostly_clear": {
          "label": "大部分晴天",
          "pct": 5.1
        },
        "partly_cloudy": {
          "label": "部分多云",
          "pct": 6.3
        },
        "mostly_cloudy": {
          "label": "大部分多云",
          "pct": 12.5
        },
        "overcast": {
          "label": "阴天",
          "pct": 38.0
        }
      },
      "humidity_comfort": {
        "dry": {
          "label": "干燥",
          "pct": 100.0
        },
        "comfortable": {
          "label": "舒适",
          "pct": 0.0
        },
        "humid": {
          "label": "潮湿",
          "pct": 0.0
        },
        "muggy": {
          "label": "闷热",
          "pct": 0.0
        },
        "oppressive": {
          "label": "闷热难受",
          "pct": 0.0
        },
        "miserable": {
          "label": "极为难受",
          "pct": 0.0
        }
      }
    }
  },
  "hourly_monthly": {
    "1": {
      "0": {
        "temp": 5.19,
        "apparent_temp": 4.28,
        "humidity": 84.6,
        "dew_point": 2.77,
        "cloud": 67.1,
        "opaque_cloud": 81.0,
        "wind": 1.75,
        "precip": 0.058,
        "tourism_score": 3.2
      },
      "1": {
        "temp": 4.7,
        "apparent_temp": 3.72,
        "humidity": 85.6,
        "dew_point": 2.55,
        "cloud": 68.7,
        "opaque_cloud": 83.5,
        "wind": 1.69,
        "precip": 0.077,
        "tourism_score": 3.0
      },
      "2": {
        "temp": 4.43,
        "apparent_temp": 3.43,
        "humidity": 86.5,
        "dew_point": 2.33,
        "cloud": 71.0,
        "opaque_cloud": 86.5,
        "wind": 1.58,
        "precip": 0.097,
        "tourism_score": 2.9
      },
      "3": {
        "temp": 4.43,
        "apparent_temp": 3.38,
        "humidity": 86.0,
        "dew_point": 2.32,
        "cloud": 68.7,
        "opaque_cloud": 83.9,
        "wind": 1.56,
        "precip": 0.1,
        "tourism_score": 2.9
      },
      "4": {
        "temp": 4.1,
        "apparent_temp": 3.06,
        "humidity": 86.4,
        "dew_point": 2.08,
        "cloud": 71.6,
        "opaque_cloud": 85.2,
        "wind": 1.52,
        "precip": 0.1,
        "tourism_score": 2.9
      },
      "5": {
        "temp": 4.65,
        "apparent_temp": 3.35,
        "humidity": 88.4,
        "dew_point": 3.04,
        "cloud": 67.7,
        "opaque_cloud": 67.7,
        "wind": 1.96,
        "precip": 0.11,
        "tourism_score": 3.3
      },
      "6": {
        "temp": 4.65,
        "apparent_temp": 3.5,
        "humidity": 87.7,
        "dew_point": 2.95,
        "cloud": 71.0,
        "opaque_cloud": 87.7,
        "wind": 1.84,
        "precip": 0.142,
        "tourism_score": 2.8
      },
      "7": {
        "temp": 4.46,
        "apparent_temp": 3.31,
        "humidity": 87.6,
        "dew_point": 2.81,
        "cloud": 70.3,
        "opaque_cloud": 84.8,
        "wind": 1.77,
        "precip": 0.155,
        "tourism_score": 2.8
      },
      "8": {
        "temp": 4.52,
        "apparent_temp": 3.27,
        "humidity": 87.5,
        "dew_point": 2.61,
        "cloud": 66.1,
        "opaque_cloud": 69.4,
        "wind": 1.81,
        "precip": 0.155,
        "tourism_score": 3.2
      },
      "9": {
        "temp": 4.87,
        "apparent_temp": 3.51,
        "humidity": 81.5,
        "dew_point": 2.12,
        "cloud": 66.1,
        "opaque_cloud": 75.8,
        "wind": 1.98,
        "precip": 0.139,
        "tourism_score": 3.2
      },
      "10": {
        "temp": 6.64,
        "apparent_temp": 5.4,
        "humidity": 75.6,
        "dew_point": 2.06,
        "cloud": 58.7,
        "opaque_cloud": 66.1,
        "wind": 2.16,
        "precip": 0.126,
        "tourism_score": 3.6
      },
      "11": {
        "temp": 7.62,
        "apparent_temp": 6.27,
        "humidity": 71.3,
        "dew_point": 2.33,
        "cloud": 56.1,
        "opaque_cloud": 58.7,
        "wind": 2.34,
        "precip": 0.126,
        "tourism_score": 3.8
      },
      "12": {
        "temp": 8.17,
        "apparent_temp": 6.93,
        "humidity": 69.6,
        "dew_point": 2.57,
        "cloud": 52.3,
        "opaque_cloud": 56.8,
        "wind": 2.49,
        "precip": 0.132,
        "tourism_score": 3.9
      },
      "13": {
        "temp": 8.93,
        "apparent_temp": 7.79,
        "humidity": 65.9,
        "dew_point": 2.25,
        "cloud": 50.3,
        "opaque_cloud": 51.0,
        "wind": 2.65,
        "precip": 0.145,
        "tourism_score": 4.1
      },
      "14": {
        "temp": 9.4,
        "apparent_temp": 8.41,
        "humidity": 65.4,
        "dew_point": 2.42,
        "cloud": 68.7,
        "opaque_cloud": 68.7,
        "wind": 2.81,
        "precip": 0.139,
        "tourism_score": 3.8
      },
      "15": {
        "temp": 9.63,
        "apparent_temp": 8.74,
        "humidity": 65.8,
        "dew_point": 2.69,
        "cloud": 50.0,
        "opaque_cloud": 51.6,
        "wind": 2.46,
        "precip": 0.152,
        "tourism_score": 4.3
      },
      "16": {
        "temp": 9.46,
        "apparent_temp": 8.62,
        "humidity": 67.4,
        "dew_point": 2.87,
        "cloud": 50.3,
        "opaque_cloud": 52.9,
        "wind": 2.2,
        "precip": 0.123,
        "tourism_score": 4.4
      },
      "17": {
        "temp": 9.25,
        "apparent_temp": 8.37,
        "humidity": 68.9,
        "dew_point": 2.96,
        "cloud": 69.4,
        "opaque_cloud": 71.0,
        "wind": 1.94,
        "precip": 0.1,
        "tourism_score": 3.9
      },
      "18": {
        "temp": 7.48,
        "apparent_temp": 6.62,
        "humidity": 75.7,
        "dew_point": 3.34,
        "cloud": 55.5,
        "opaque_cloud": 67.4,
        "wind": 1.7,
        "precip": 0.097,
        "tourism_score": 3.7
      },
      "19": {
        "temp": 7.05,
        "apparent_temp": 6.15,
        "humidity": 76.4,
        "dew_point": 3.06,
        "cloud": 56.5,
        "opaque_cloud": 68.7,
        "wind": 1.72,
        "precip": 0.081,
        "tourism_score": 3.7
      },
      "20": {
        "temp": 6.83,
        "apparent_temp": 6.0,
        "humidity": 76.8,
        "dew_point": 2.91,
        "cloud": 58.7,
        "opaque_cloud": 69.7,
        "wind": 1.67,
        "precip": 0.09,
        "tourism_score": 3.6
      },
      "21": {
        "temp": 6.58,
        "apparent_temp": 5.81,
        "humidity": 77.9,
        "dew_point": 2.92,
        "cloud": 58.4,
        "opaque_cloud": 70.6,
        "wind": 1.6,
        "precip": 0.113,
        "tourism_score": 3.5
      },
      "22": {
        "temp": 5.9,
        "apparent_temp": 5.06,
        "humidity": 80.1,
        "dew_point": 2.68,
        "cloud": 64.2,
        "opaque_cloud": 74.8,
        "wind": 1.65,
        "precip": 0.097,
        "tourism_score": 3.3
      },
      "23": {
        "temp": 5.01,
        "apparent_temp": 4.01,
        "humidity": 83.9,
        "dew_point": 2.47,
        "cloud": 68.4,
        "opaque_cloud": 81.6,
        "wind": 1.68,
        "precip": 0.094,
        "tourism_score": 3.0
      }
    },
    "2": {
      "0": {
        "temp": 6.24,
        "apparent_temp": 5.32,
        "humidity": 80.9,
        "dew_point": 3.03,
        "cloud": 73.9,
        "opaque_cloud": 75.7,
        "wind": 1.58,
        "precip": 0.139,
        "tourism_score": 3.2
      },
      "1": {
        "temp": 5.99,
        "apparent_temp": 5.13,
        "humidity": 81.9,
        "dew_point": 2.98,
        "cloud": 72.9,
        "opaque_cloud": 77.1,
        "wind": 1.52,
        "precip": 0.139,
        "tourism_score": 3.1
      },
      "2": {
        "temp": 5.75,
        "apparent_temp": 4.83,
        "humidity": 82.8,
        "dew_point": 2.91,
        "cloud": 72.5,
        "opaque_cloud": 78.6,
        "wind": 1.48,
        "precip": 0.132,
        "tourism_score": 3.1
      },
      "3": {
        "temp": 5.81,
        "apparent_temp": 4.93,
        "humidity": 82.9,
        "dew_point": 2.99,
        "cloud": 71.4,
        "opaque_cloud": 78.6,
        "wind": 1.5,
        "precip": 0.168,
        "tourism_score": 3.0
      },
      "4": {
        "temp": 5.39,
        "apparent_temp": 4.42,
        "humidity": 84.3,
        "dew_point": 2.86,
        "cloud": 74.6,
        "opaque_cloud": 79.6,
        "wind": 1.48,
        "precip": 0.157,
        "tourism_score": 3.0
      },
      "5": {
        "temp": 5.38,
        "apparent_temp": 4.32,
        "humidity": 83.8,
        "dew_point": 2.76,
        "cloud": 74.6,
        "opaque_cloud": 79.6,
        "wind": 1.51,
        "precip": 0.154,
        "tourism_score": 3.0
      },
      "6": {
        "temp": 5.15,
        "apparent_temp": 4.19,
        "humidity": 84.4,
        "dew_point": 2.64,
        "cloud": 76.4,
        "opaque_cloud": 82.1,
        "wind": 1.46,
        "precip": 0.143,
        "tourism_score": 3.0
      },
      "7": {
        "temp": 5.12,
        "apparent_temp": 4.08,
        "humidity": 84.5,
        "dew_point": 2.65,
        "cloud": 73.9,
        "opaque_cloud": 82.1,
        "wind": 1.53,
        "precip": 0.157,
        "tourism_score": 3.0
      },
      "8": {
        "temp": 5.49,
        "apparent_temp": 4.28,
        "humidity": 83.4,
        "dew_point": 2.84,
        "cloud": 71.4,
        "opaque_cloud": 80.7,
        "wind": 1.67,
        "precip": 0.157,
        "tourism_score": 3.1
      },
      "9": {
        "temp": 5.91,
        "apparent_temp": 4.65,
        "humidity": 81.2,
        "dew_point": 2.85,
        "cloud": 65.4,
        "opaque_cloud": 76.4,
        "wind": 1.79,
        "precip": 0.129,
        "tourism_score": 3.2
      },
      "10": {
        "temp": 8.66,
        "apparent_temp": 7.64,
        "humidity": 69.6,
        "dew_point": 3.06,
        "cloud": 53.6,
        "opaque_cloud": 57.1,
        "wind": 1.96,
        "precip": 0.146,
        "tourism_score": 4.1
      },
      "11": {
        "temp": 9.05,
        "apparent_temp": 8.05,
        "humidity": 67.6,
        "dew_point": 2.91,
        "cloud": 52.1,
        "opaque_cloud": 54.6,
        "wind": 2.07,
        "precip": 0.15,
        "tourism_score": 4.2
      },
      "12": {
        "temp": 9.12,
        "apparent_temp": 8.14,
        "humidity": 66.8,
        "dew_point": 2.77,
        "cloud": 50.7,
        "opaque_cloud": 51.8,
        "wind": 2.2,
        "precip": 0.182,
        "tourism_score": 4.3
      },
      "13": {
        "temp": 10.93,
        "apparent_temp": 10.13,
        "humidity": 59.8,
        "dew_point": 2.59,
        "cloud": 47.1,
        "opaque_cloud": 41.4,
        "wind": 2.33,
        "precip": 0.186,
        "tourism_score": 5.1
      },
      "14": {
        "temp": 11.19,
        "apparent_temp": 10.4,
        "humidity": 59.2,
        "dew_point": 2.62,
        "cloud": 41.4,
        "opaque_cloud": 41.8,
        "wind": 2.35,
        "precip": 0.196,
        "tourism_score": 5.2
      },
      "15": {
        "temp": 11.18,
        "apparent_temp": 10.41,
        "humidity": 59.6,
        "dew_point": 2.65,
        "cloud": 40.7,
        "opaque_cloud": 41.1,
        "wind": 2.27,
        "precip": 0.3,
        "tourism_score": 5.0
      },
      "16": {
        "temp": 11.07,
        "apparent_temp": 10.31,
        "humidity": 61.6,
        "dew_point": 3.06,
        "cloud": 45.0,
        "opaque_cloud": 44.6,
        "wind": 2.15,
        "precip": 0.264,
        "tourism_score": 4.9
      },
      "17": {
        "temp": 11.05,
        "apparent_temp": 10.38,
        "humidity": 62.4,
        "dew_point": 3.28,
        "cloud": 48.2,
        "opaque_cloud": 45.4,
        "wind": 1.8,
        "precip": 0.236,
        "tourism_score": 4.9
      },
      "18": {
        "temp": 8.74,
        "apparent_temp": 7.81,
        "humidity": 72.6,
        "dew_point": 3.71,
        "cloud": 63.9,
        "opaque_cloud": 62.1,
        "wind": 1.96,
        "precip": 0.189,
        "tourism_score": 3.8
      },
      "19": {
        "temp": 8.74,
        "apparent_temp": 7.87,
        "humidity": 72.5,
        "dew_point": 3.67,
        "cloud": 60.7,
        "opaque_cloud": 62.1,
        "wind": 1.94,
        "precip": 0.171,
        "tourism_score": 3.9
      },
      "20": {
        "temp": 8.51,
        "apparent_temp": 7.65,
        "humidity": 74.0,
        "dew_point": 3.82,
        "cloud": 63.9,
        "opaque_cloud": 64.6,
        "wind": 1.84,
        "precip": 0.161,
        "tourism_score": 3.8
      },
      "21": {
        "temp": 8.13,
        "apparent_temp": 7.29,
        "humidity": 75.5,
        "dew_point": 3.81,
        "cloud": 66.8,
        "opaque_cloud": 67.5,
        "wind": 1.76,
        "precip": 0.179,
        "tourism_score": 3.6
      },
      "22": {
        "temp": 7.69,
        "apparent_temp": 6.93,
        "humidity": 76.9,
        "dew_point": 3.69,
        "cloud": 67.5,
        "opaque_cloud": 70.0,
        "wind": 1.62,
        "precip": 0.171,
        "tourism_score": 3.4
      },
      "23": {
        "temp": 6.48,
        "apparent_temp": 5.62,
        "humidity": 80.8,
        "dew_point": 3.23,
        "cloud": 73.2,
        "opaque_cloud": 76.4,
        "wind": 1.59,
        "precip": 0.175,
        "tourism_score": 3.0
      }
    },
    "3": {
      "0": {
        "temp": 10.43,
        "apparent_temp": 9.96,
        "humidity": 84.5,
        "dew_point": 7.81,
        "cloud": 79.4,
        "opaque_cloud": 81.9,
        "wind": 1.65,
        "precip": 0.187,
        "tourism_score": 3.8
      },
      "1": {
        "temp": 10.29,
        "apparent_temp": 9.79,
        "humidity": 84.9,
        "dew_point": 7.76,
        "cloud": 78.7,
        "opaque_cloud": 82.3,
        "wind": 1.66,
        "precip": 0.2,
        "tourism_score": 3.7
      },
      "2": {
        "temp": 10.25,
        "apparent_temp": 9.68,
        "humidity": 85.2,
        "dew_point": 7.77,
        "cloud": 81.0,
        "opaque_cloud": 83.2,
        "wind": 1.71,
        "precip": 0.265,
        "tourism_score": 3.5
      },
      "3": {
        "temp": 10.16,
        "apparent_temp": 9.6,
        "humidity": 85.4,
        "dew_point": 7.72,
        "cloud": 78.4,
        "opaque_cloud": 83.2,
        "wind": 1.7,
        "precip": 0.374,
        "tourism_score": 3.3
      },
      "4": {
        "temp": 10.04,
        "apparent_temp": 9.51,
        "humidity": 85.9,
        "dew_point": 7.68,
        "cloud": 77.7,
        "opaque_cloud": 83.9,
        "wind": 1.7,
        "precip": 0.339,
        "tourism_score": 3.3
      },
      "5": {
        "temp": 9.0,
        "apparent_temp": 8.05,
        "humidity": 90.1,
        "dew_point": 7.4,
        "cloud": 81.6,
        "opaque_cloud": 81.6,
        "wind": 2.53,
        "precip": 0.377,
        "tourism_score": 3.1
      },
      "6": {
        "temp": 9.75,
        "apparent_temp": 8.92,
        "humidity": 89.3,
        "dew_point": 8.12,
        "cloud": 81.0,
        "opaque_cloud": 89.0,
        "wind": 2.43,
        "precip": 0.697,
        "tourism_score": 2.9
      },
      "7": {
        "temp": 9.91,
        "apparent_temp": 9.15,
        "humidity": 87.8,
        "dew_point": 7.98,
        "cloud": 84.2,
        "opaque_cloud": 87.4,
        "wind": 2.31,
        "precip": 0.503,
        "tourism_score": 3.1
      },
      "8": {
        "temp": 10.02,
        "apparent_temp": 9.29,
        "humidity": 87.0,
        "dew_point": 8.0,
        "cloud": 86.5,
        "opaque_cloud": 86.5,
        "wind": 2.19,
        "precip": 0.313,
        "tourism_score": 3.1
      },
      "9": {
        "temp": 10.49,
        "apparent_temp": 9.77,
        "humidity": 84.5,
        "dew_point": 8.04,
        "cloud": 77.1,
        "opaque_cloud": 81.3,
        "wind": 2.28,
        "precip": 0.374,
        "tourism_score": 3.5
      },
      "10": {
        "temp": 11.08,
        "apparent_temp": 10.34,
        "humidity": 81.5,
        "dew_point": 8.05,
        "cloud": 75.2,
        "opaque_cloud": 77.1,
        "wind": 2.35,
        "precip": 0.323,
        "tourism_score": 3.8
      },
      "11": {
        "temp": 12.9,
        "apparent_temp": 12.34,
        "humidity": 75.9,
        "dew_point": 8.46,
        "cloud": 70.3,
        "opaque_cloud": 70.6,
        "wind": 2.44,
        "precip": 0.287,
        "tourism_score": 4.6
      },
      "12": {
        "temp": 13.17,
        "apparent_temp": 12.69,
        "humidity": 74.3,
        "dew_point": 8.36,
        "cloud": 68.4,
        "opaque_cloud": 65.2,
        "wind": 2.47,
        "precip": 0.2,
        "tourism_score": 5.0
      },
      "13": {
        "temp": 13.43,
        "apparent_temp": 13.04,
        "humidity": 73.0,
        "dew_point": 8.33,
        "cloud": 63.5,
        "opaque_cloud": 63.5,
        "wind": 2.49,
        "precip": 0.206,
        "tourism_score": 5.3
      },
      "14": {
        "temp": 13.96,
        "apparent_temp": 13.6,
        "humidity": 71.2,
        "dew_point": 8.44,
        "cloud": 84.5,
        "opaque_cloud": 84.5,
        "wind": 2.53,
        "precip": 0.223,
        "tourism_score": 4.9
      },
      "15": {
        "temp": 13.99,
        "apparent_temp": 13.72,
        "humidity": 72.0,
        "dew_point": 8.62,
        "cloud": 60.3,
        "opaque_cloud": 61.3,
        "wind": 2.63,
        "precip": 0.31,
        "tourism_score": 5.5
      },
      "16": {
        "temp": 14.1,
        "apparent_temp": 13.86,
        "humidity": 72.7,
        "dew_point": 8.6,
        "cloud": 62.3,
        "opaque_cloud": 62.9,
        "wind": 2.71,
        "precip": 0.374,
        "tourism_score": 5.4
      },
      "17": {
        "temp": 13.92,
        "apparent_temp": 13.73,
        "humidity": 74.9,
        "dew_point": 8.98,
        "cloud": 86.5,
        "opaque_cloud": 86.5,
        "wind": 2.8,
        "precip": 0.271,
        "tourism_score": 4.8
      },
      "18": {
        "temp": 12.94,
        "apparent_temp": 12.81,
        "humidity": 78.8,
        "dew_point": 9.1,
        "cloud": 70.0,
        "opaque_cloud": 71.9,
        "wind": 1.71,
        "precip": 0.2,
        "tourism_score": 4.8
      },
      "19": {
        "temp": 12.71,
        "apparent_temp": 12.55,
        "humidity": 78.8,
        "dew_point": 8.88,
        "cloud": 70.6,
        "opaque_cloud": 71.6,
        "wind": 1.88,
        "precip": 0.152,
        "tourism_score": 4.8
      },
      "20": {
        "temp": 12.61,
        "apparent_temp": 12.42,
        "humidity": 79.8,
        "dew_point": 8.98,
        "cloud": 69.7,
        "opaque_cloud": 70.6,
        "wind": 1.95,
        "precip": 0.174,
        "tourism_score": 4.8
      },
      "21": {
        "temp": 12.36,
        "apparent_temp": 12.2,
        "humidity": 80.1,
        "dew_point": 8.82,
        "cloud": 71.9,
        "opaque_cloud": 73.9,
        "wind": 1.75,
        "precip": 0.184,
        "tourism_score": 4.6
      },
      "22": {
        "temp": 12.13,
        "apparent_temp": 11.96,
        "humidity": 81.2,
        "dew_point": 8.82,
        "cloud": 73.9,
        "opaque_cloud": 75.8,
        "wind": 1.59,
        "precip": 0.174,
        "tourism_score": 4.5
      },
      "23": {
        "temp": 10.93,
        "apparent_temp": 10.59,
        "humidity": 86.0,
        "dew_point": 8.58,
        "cloud": 81.9,
        "opaque_cloud": 84.5,
        "wind": 1.57,
        "precip": 0.19,
        "tourism_score": 3.8
      }
    },
    "4": {
      "0": {
        "temp": 15.73,
        "apparent_temp": 15.73,
        "humidity": 85.0,
        "dew_point": 13.12,
        "cloud": 76.0,
        "opaque_cloud": 83.3,
        "wind": 1.85,
        "precip": 0.367,
        "tourism_score": 5.6
      },
      "1": {
        "temp": 15.61,
        "apparent_temp": 15.58,
        "humidity": 85.0,
        "dew_point": 13.03,
        "cloud": 75.0,
        "opaque_cloud": 83.0,
        "wind": 1.88,
        "precip": 0.263,
        "tourism_score": 5.7
      },
      "2": {
        "temp": 15.54,
        "apparent_temp": 15.5,
        "humidity": 84.9,
        "dew_point": 12.91,
        "cloud": 72.3,
        "opaque_cloud": 78.7,
        "wind": 1.9,
        "precip": 0.227,
        "tourism_score": 5.8
      },
      "3": {
        "temp": 15.49,
        "apparent_temp": 15.44,
        "humidity": 84.9,
        "dew_point": 12.87,
        "cloud": 71.7,
        "opaque_cloud": 82.0,
        "wind": 1.84,
        "precip": 0.19,
        "tourism_score": 5.6
      },
      "4": {
        "temp": 15.43,
        "apparent_temp": 15.38,
        "humidity": 85.0,
        "dew_point": 12.83,
        "cloud": 70.7,
        "opaque_cloud": 82.3,
        "wind": 1.68,
        "precip": 0.247,
        "tourism_score": 5.5
      },
      "5": {
        "temp": 14.15,
        "apparent_temp": 13.67,
        "humidity": 88.1,
        "dew_point": 12.2,
        "cloud": 83.0,
        "opaque_cloud": 83.0,
        "wind": 2.29,
        "precip": 0.22,
        "tourism_score": 5.0
      },
      "6": {
        "temp": 15.82,
        "apparent_temp": 15.48,
        "humidity": 86.4,
        "dew_point": 13.45,
        "cloud": 73.7,
        "opaque_cloud": 84.3,
        "wind": 2.48,
        "precip": 0.23,
        "tourism_score": 5.7
      },
      "7": {
        "temp": 16.12,
        "apparent_temp": 15.9,
        "humidity": 84.5,
        "dew_point": 13.37,
        "cloud": 74.3,
        "opaque_cloud": 80.3,
        "wind": 2.63,
        "precip": 0.26,
        "tourism_score": 5.9
      },
      "8": {
        "temp": 16.37,
        "apparent_temp": 16.11,
        "humidity": 82.7,
        "dew_point": 13.23,
        "cloud": 80.0,
        "opaque_cloud": 80.0,
        "wind": 2.67,
        "precip": 0.31,
        "tourism_score": 5.9
      },
      "9": {
        "temp": 17.04,
        "apparent_temp": 17.02,
        "humidity": 80.1,
        "dew_point": 13.38,
        "cloud": 68.7,
        "opaque_cloud": 74.0,
        "wind": 2.7,
        "precip": 0.3,
        "tourism_score": 6.3
      },
      "10": {
        "temp": 17.88,
        "apparent_temp": 17.97,
        "humidity": 78.9,
        "dew_point": 14.0,
        "cloud": 66.0,
        "opaque_cloud": 72.7,
        "wind": 2.74,
        "precip": 0.28,
        "tourism_score": 6.6
      },
      "11": {
        "temp": 18.67,
        "apparent_temp": 18.69,
        "humidity": 72.7,
        "dew_point": 13.22,
        "cloud": 59.7,
        "opaque_cloud": 61.3,
        "wind": 2.77,
        "precip": 0.303,
        "tourism_score": 7.1
      },
      "12": {
        "temp": 19.2,
        "apparent_temp": 19.22,
        "humidity": 73.5,
        "dew_point": 13.84,
        "cloud": 59.7,
        "opaque_cloud": 63.0,
        "wind": 2.81,
        "precip": 0.287,
        "tourism_score": 7.0
      },
      "13": {
        "temp": 19.88,
        "apparent_temp": 19.96,
        "humidity": 71.1,
        "dew_point": 14.0,
        "cloud": 59.0,
        "opaque_cloud": 60.0,
        "wind": 2.84,
        "precip": 0.28,
        "tourism_score": 7.0
      },
      "14": {
        "temp": 20.42,
        "apparent_temp": 20.56,
        "humidity": 68.7,
        "dew_point": 13.89,
        "cloud": 76.3,
        "opaque_cloud": 76.3,
        "wind": 2.88,
        "precip": 0.323,
        "tourism_score": 6.3
      },
      "15": {
        "temp": 20.5,
        "apparent_temp": 20.64,
        "humidity": 70.0,
        "dew_point": 14.21,
        "cloud": 56.3,
        "opaque_cloud": 57.7,
        "wind": 2.73,
        "precip": 0.423,
        "tourism_score": 6.7
      },
      "16": {
        "temp": 20.56,
        "apparent_temp": 20.71,
        "humidity": 69.9,
        "dew_point": 14.3,
        "cloud": 56.3,
        "opaque_cloud": 57.7,
        "wind": 2.58,
        "precip": 0.37,
        "tourism_score": 6.7
      },
      "17": {
        "temp": 20.63,
        "apparent_temp": 20.87,
        "humidity": 70.2,
        "dew_point": 14.56,
        "cloud": 81.3,
        "opaque_cloud": 81.3,
        "wind": 2.43,
        "precip": 0.307,
        "tourism_score": 6.0
      },
      "18": {
        "temp": 19.02,
        "apparent_temp": 19.1,
        "humidity": 76.8,
        "dew_point": 14.64,
        "cloud": 65.7,
        "opaque_cloud": 69.7,
        "wind": 1.69,
        "precip": 0.25,
        "tourism_score": 6.8
      },
      "19": {
        "temp": 18.95,
        "apparent_temp": 19.0,
        "humidity": 75.5,
        "dew_point": 14.25,
        "cloud": 59.7,
        "opaque_cloud": 67.0,
        "wind": 1.84,
        "precip": 0.217,
        "tourism_score": 7.0
      },
      "20": {
        "temp": 18.73,
        "apparent_temp": 18.73,
        "humidity": 76.1,
        "dew_point": 14.19,
        "cloud": 59.7,
        "opaque_cloud": 66.0,
        "wind": 1.91,
        "precip": 0.187,
        "tourism_score": 7.1
      },
      "21": {
        "temp": 18.51,
        "apparent_temp": 18.51,
        "humidity": 76.6,
        "dew_point": 14.07,
        "cloud": 63.3,
        "opaque_cloud": 69.7,
        "wind": 1.83,
        "precip": 0.207,
        "tourism_score": 7.0
      },
      "22": {
        "temp": 18.15,
        "apparent_temp": 18.15,
        "humidity": 77.9,
        "dew_point": 14.01,
        "cloud": 65.0,
        "opaque_cloud": 71.0,
        "wind": 1.8,
        "precip": 0.267,
        "tourism_score": 6.9
      },
      "23": {
        "temp": 15.83,
        "apparent_temp": 15.83,
        "humidity": 85.3,
        "dew_point": 13.26,
        "cloud": 69.7,
        "opaque_cloud": 82.7,
        "wind": 1.81,
        "precip": 0.313,
        "tourism_score": 5.7
      }
    },
    "5": {
      "0": {
        "temp": 20.36,
        "apparent_temp": 20.36,
        "humidity": 85.9,
        "dew_point": 17.86,
        "cloud": 77.7,
        "opaque_cloud": 84.5,
        "wind": 1.55,
        "precip": 0.371,
        "tourism_score": 7.1
      },
      "1": {
        "temp": 19.92,
        "apparent_temp": 19.92,
        "humidity": 87.3,
        "dew_point": 17.69,
        "cloud": 78.4,
        "opaque_cloud": 86.8,
        "wind": 1.57,
        "precip": 0.397,
        "tourism_score": 6.9
      },
      "2": {
        "temp": 19.55,
        "apparent_temp": 19.55,
        "humidity": 87.9,
        "dew_point": 17.45,
        "cloud": 84.5,
        "opaque_cloud": 87.7,
        "wind": 1.79,
        "precip": 0.458,
        "tourism_score": 6.6
      },
      "3": {
        "temp": 19.48,
        "apparent_temp": 19.48,
        "humidity": 88.4,
        "dew_point": 17.47,
        "cloud": 83.5,
        "opaque_cloud": 88.1,
        "wind": 1.72,
        "precip": 0.2,
        "tourism_score": 6.9
      },
      "4": {
        "temp": 19.18,
        "apparent_temp": 19.18,
        "humidity": 89.9,
        "dew_point": 17.46,
        "cloud": 88.1,
        "opaque_cloud": 90.6,
        "wind": 1.65,
        "precip": 0.274,
        "tourism_score": 6.8
      },
      "5": {
        "temp": 19.79,
        "apparent_temp": 19.79,
        "humidity": 90.1,
        "dew_point": 18.07,
        "cloud": 77.4,
        "opaque_cloud": 77.4,
        "wind": 1.91,
        "precip": 0.329,
        "tourism_score": 7.2
      },
      "6": {
        "temp": 20.28,
        "apparent_temp": 20.28,
        "humidity": 87.4,
        "dew_point": 18.05,
        "cloud": 83.5,
        "opaque_cloud": 84.8,
        "wind": 1.92,
        "precip": 0.332,
        "tourism_score": 7.2
      },
      "7": {
        "temp": 20.62,
        "apparent_temp": 20.62,
        "humidity": 86.2,
        "dew_point": 18.15,
        "cloud": 81.6,
        "opaque_cloud": 83.9,
        "wind": 1.98,
        "precip": 0.361,
        "tourism_score": 7.2
      },
      "8": {
        "temp": 21.05,
        "apparent_temp": 21.11,
        "humidity": 85.3,
        "dew_point": 18.39,
        "cloud": 79.0,
        "opaque_cloud": 79.0,
        "wind": 2.15,
        "precip": 0.358,
        "tourism_score": 7.3
      },
      "9": {
        "temp": 21.82,
        "apparent_temp": 21.98,
        "humidity": 81.6,
        "dew_point": 18.39,
        "cloud": 75.2,
        "opaque_cloud": 76.5,
        "wind": 2.25,
        "precip": 0.332,
        "tourism_score": 7.3
      },
      "10": {
        "temp": 22.61,
        "apparent_temp": 22.88,
        "humidity": 77.3,
        "dew_point": 18.21,
        "cloud": 67.4,
        "opaque_cloud": 69.0,
        "wind": 2.35,
        "precip": 0.281,
        "tourism_score": 7.4
      },
      "11": {
        "temp": 23.42,
        "apparent_temp": 23.85,
        "humidity": 73.0,
        "dew_point": 17.99,
        "cloud": 63.5,
        "opaque_cloud": 62.6,
        "wind": 2.46,
        "precip": 0.268,
        "tourism_score": 7.4
      },
      "12": {
        "temp": 24.17,
        "apparent_temp": 24.75,
        "humidity": 70.6,
        "dew_point": 18.14,
        "cloud": 60.3,
        "opaque_cloud": 58.4,
        "wind": 2.58,
        "precip": 0.223,
        "tourism_score": 7.4
      },
      "13": {
        "temp": 24.95,
        "apparent_temp": 25.81,
        "humidity": 66.9,
        "dew_point": 17.97,
        "cloud": 52.6,
        "opaque_cloud": 52.3,
        "wind": 2.68,
        "precip": 0.206,
        "tourism_score": 7.1
      },
      "14": {
        "temp": 25.71,
        "apparent_temp": 26.86,
        "humidity": 65.3,
        "dew_point": 18.19,
        "cloud": 74.2,
        "opaque_cloud": 74.2,
        "wind": 2.78,
        "precip": 0.345,
        "tourism_score": 6.1
      },
      "15": {
        "temp": 25.58,
        "apparent_temp": 26.58,
        "humidity": 65.2,
        "dew_point": 18.03,
        "cloud": 50.0,
        "opaque_cloud": 49.7,
        "wind": 2.69,
        "precip": 0.265,
        "tourism_score": 6.9
      },
      "16": {
        "temp": 25.58,
        "apparent_temp": 26.52,
        "humidity": 65.6,
        "dew_point": 18.07,
        "cloud": 51.3,
        "opaque_cloud": 49.7,
        "wind": 2.67,
        "precip": 0.274,
        "tourism_score": 7.0
      },
      "17": {
        "temp": 25.5,
        "apparent_temp": 26.46,
        "humidity": 66.9,
        "dew_point": 18.23,
        "cloud": 74.5,
        "opaque_cloud": 74.5,
        "wind": 2.67,
        "precip": 0.297,
        "tourism_score": 6.4
      },
      "18": {
        "temp": 23.1,
        "apparent_temp": 23.48,
        "humidity": 77.2,
        "dew_point": 18.74,
        "cloud": 70.3,
        "opaque_cloud": 70.0,
        "wind": 1.61,
        "precip": 0.539,
        "tourism_score": 7.3
      },
      "19": {
        "temp": 22.81,
        "apparent_temp": 23.15,
        "humidity": 77.1,
        "dew_point": 18.39,
        "cloud": 70.0,
        "opaque_cloud": 68.7,
        "wind": 1.71,
        "precip": 0.487,
        "tourism_score": 7.4
      },
      "20": {
        "temp": 22.8,
        "apparent_temp": 23.12,
        "humidity": 76.5,
        "dew_point": 18.26,
        "cloud": 68.4,
        "opaque_cloud": 68.4,
        "wind": 1.68,
        "precip": 0.416,
        "tourism_score": 7.5
      },
      "21": {
        "temp": 22.81,
        "apparent_temp": 23.13,
        "humidity": 76.2,
        "dew_point": 18.2,
        "cloud": 67.7,
        "opaque_cloud": 67.7,
        "wind": 1.66,
        "precip": 0.394,
        "tourism_score": 7.5
      },
      "22": {
        "temp": 22.07,
        "apparent_temp": 22.36,
        "humidity": 79.1,
        "dew_point": 18.13,
        "cloud": 70.6,
        "opaque_cloud": 72.6,
        "wind": 1.65,
        "precip": 0.345,
        "tourism_score": 7.5
      },
      "23": {
        "temp": 20.66,
        "apparent_temp": 20.66,
        "humidity": 84.3,
        "dew_point": 17.83,
        "cloud": 72.3,
        "opaque_cloud": 81.3,
        "wind": 1.51,
        "precip": 0.29,
        "tourism_score": 7.5
      }
    },
    "6": {
      "0": {
        "temp": 23.49,
        "apparent_temp": 23.55,
        "humidity": 87.5,
        "dew_point": 21.22,
        "cloud": 86.3,
        "opaque_cloud": 87.0,
        "wind": 1.37,
        "precip": 0.31,
        "tourism_score": 7.3
      },
      "1": {
        "temp": 23.09,
        "apparent_temp": 23.09,
        "humidity": 88.8,
        "dew_point": 21.06,
        "cloud": 88.0,
        "opaque_cloud": 89.3,
        "wind": 1.36,
        "precip": 0.353,
        "tourism_score": 7.3
      },
      "2": {
        "temp": 22.72,
        "apparent_temp": 22.72,
        "humidity": 89.8,
        "dew_point": 20.92,
        "cloud": 87.3,
        "opaque_cloud": 90.0,
        "wind": 1.34,
        "precip": 0.45,
        "tourism_score": 7.2
      },
      "3": {
        "temp": 22.7,
        "apparent_temp": 22.7,
        "humidity": 89.8,
        "dew_point": 20.89,
        "cloud": 86.3,
        "opaque_cloud": 90.0,
        "wind": 1.3,
        "precip": 0.397,
        "tourism_score": 7.3
      },
      "4": {
        "temp": 22.53,
        "apparent_temp": 22.53,
        "humidity": 90.3,
        "dew_point": 20.82,
        "cloud": 88.0,
        "opaque_cloud": 92.0,
        "wind": 1.3,
        "precip": 0.387,
        "tourism_score": 7.3
      },
      "5": {
        "temp": 23.59,
        "apparent_temp": 24.2,
        "humidity": 88.2,
        "dew_point": 21.41,
        "cloud": 85.0,
        "opaque_cloud": 85.0,
        "wind": 2.11,
        "precip": 0.403,
        "tourism_score": 7.0
      },
      "6": {
        "temp": 24.29,
        "apparent_temp": 25.11,
        "humidity": 85.1,
        "dew_point": 21.49,
        "cloud": 77.3,
        "opaque_cloud": 82.3,
        "wind": 2.17,
        "precip": 0.503,
        "tourism_score": 6.6
      },
      "7": {
        "temp": 24.68,
        "apparent_temp": 25.39,
        "humidity": 82.6,
        "dew_point": 21.34,
        "cloud": 73.7,
        "opaque_cloud": 78.0,
        "wind": 2.27,
        "precip": 0.717,
        "tourism_score": 6.8
      },
      "8": {
        "temp": 25.19,
        "apparent_temp": 26.19,
        "humidity": 80.5,
        "dew_point": 21.39,
        "cloud": 81.0,
        "opaque_cloud": 81.0,
        "wind": 2.4,
        "precip": 0.743,
        "tourism_score": 6.4
      },
      "9": {
        "temp": 25.87,
        "apparent_temp": 27.07,
        "humidity": 77.8,
        "dew_point": 21.45,
        "cloud": 64.3,
        "opaque_cloud": 70.7,
        "wind": 2.59,
        "precip": 0.62,
        "tourism_score": 6.5
      },
      "10": {
        "temp": 26.52,
        "apparent_temp": 28.13,
        "humidity": 74.6,
        "dew_point": 21.36,
        "cloud": 59.0,
        "opaque_cloud": 63.7,
        "wind": 2.78,
        "precip": 0.567,
        "tourism_score": 6.2
      },
      "11": {
        "temp": 27.2,
        "apparent_temp": 29.26,
        "humidity": 72.0,
        "dew_point": 21.31,
        "cloud": 57.3,
        "opaque_cloud": 60.7,
        "wind": 2.97,
        "precip": 0.613,
        "tourism_score": 5.7
      },
      "12": {
        "temp": 27.87,
        "apparent_temp": 30.17,
        "humidity": 69.7,
        "dew_point": 21.38,
        "cloud": 54.7,
        "opaque_cloud": 57.3,
        "wind": 3.15,
        "precip": 0.623,
        "tourism_score": 5.4
      },
      "13": {
        "temp": 28.53,
        "apparent_temp": 30.99,
        "humidity": 67.5,
        "dew_point": 21.4,
        "cloud": 51.7,
        "opaque_cloud": 53.0,
        "wind": 3.34,
        "precip": 0.513,
        "tourism_score": 5.3
      },
      "14": {
        "temp": 29.2,
        "apparent_temp": 32.05,
        "humidity": 65.6,
        "dew_point": 21.42,
        "cloud": 73.3,
        "opaque_cloud": 73.3,
        "wind": 3.52,
        "precip": 0.49,
        "tourism_score": 4.5
      },
      "15": {
        "temp": 29.11,
        "apparent_temp": 31.77,
        "humidity": 65.5,
        "dew_point": 21.23,
        "cloud": 50.0,
        "opaque_cloud": 50.3,
        "wind": 3.43,
        "precip": 0.483,
        "tourism_score": 5.1
      },
      "16": {
        "temp": 29.29,
        "apparent_temp": 31.98,
        "humidity": 65.4,
        "dew_point": 21.47,
        "cloud": 52.0,
        "opaque_cloud": 49.3,
        "wind": 3.3,
        "precip": 0.467,
        "tourism_score": 5.1
      },
      "17": {
        "temp": 29.29,
        "apparent_temp": 32.1,
        "humidity": 66.0,
        "dew_point": 21.59,
        "cloud": 78.0,
        "opaque_cloud": 78.0,
        "wind": 3.19,
        "precip": 0.577,
        "tourism_score": 4.3
      },
      "18": {
        "temp": 26.07,
        "apparent_temp": 27.55,
        "humidity": 79.7,
        "dew_point": 22.13,
        "cloud": 70.3,
        "opaque_cloud": 73.7,
        "wind": 1.56,
        "precip": 0.53,
        "tourism_score": 6.4
      },
      "19": {
        "temp": 25.71,
        "apparent_temp": 27.0,
        "humidity": 80.8,
        "dew_point": 21.98,
        "cloud": 73.3,
        "opaque_cloud": 75.7,
        "wind": 1.82,
        "precip": 0.493,
        "tourism_score": 6.5
      },
      "20": {
        "temp": 25.72,
        "apparent_temp": 27.0,
        "humidity": 81.0,
        "dew_point": 22.04,
        "cloud": 76.7,
        "opaque_cloud": 77.0,
        "wind": 2.04,
        "precip": 0.38,
        "tourism_score": 6.4
      },
      "21": {
        "temp": 25.55,
        "apparent_temp": 26.7,
        "humidity": 81.5,
        "dew_point": 21.98,
        "cloud": 74.0,
        "opaque_cloud": 76.3,
        "wind": 1.64,
        "precip": 0.28,
        "tourism_score": 6.6
      },
      "22": {
        "temp": 25.07,
        "apparent_temp": 25.9,
        "humidity": 83.4,
        "dew_point": 21.94,
        "cloud": 78.3,
        "opaque_cloud": 80.3,
        "wind": 1.5,
        "precip": 0.293,
        "tourism_score": 6.7
      },
      "23": {
        "temp": 23.84,
        "apparent_temp": 24.0,
        "humidity": 87.3,
        "dew_point": 21.51,
        "cloud": 83.7,
        "opaque_cloud": 86.3,
        "wind": 1.4,
        "precip": 0.31,
        "tourism_score": 7.2
      }
    },
    "7": {
      "0": {
        "temp": 26.66,
        "apparent_temp": 28.43,
        "humidity": 86.3,
        "dew_point": 24.14,
        "cloud": 82.9,
        "opaque_cloud": 85.8,
        "wind": 1.1,
        "precip": 0.016,
        "tourism_score": 6.1
      },
      "1": {
        "temp": 26.1,
        "apparent_temp": 26.92,
        "humidity": 88.0,
        "dew_point": 23.91,
        "cloud": 84.2,
        "opaque_cloud": 87.4,
        "wind": 1.05,
        "precip": 0.006,
        "tourism_score": 7.0
      },
      "2": {
        "temp": 25.84,
        "apparent_temp": 26.26,
        "humidity": 88.9,
        "dew_point": 23.83,
        "cloud": 81.6,
        "opaque_cloud": 88.7,
        "wind": 1.06,
        "precip": 0.023,
        "tourism_score": 7.3
      },
      "3": {
        "temp": 25.8,
        "apparent_temp": 26.49,
        "humidity": 88.7,
        "dew_point": 23.78,
        "cloud": 74.5,
        "opaque_cloud": 88.7,
        "wind": 1.08,
        "precip": 0.023,
        "tourism_score": 7.1
      },
      "4": {
        "temp": 25.47,
        "apparent_temp": 25.74,
        "humidity": 89.8,
        "dew_point": 23.65,
        "cloud": 79.4,
        "opaque_cloud": 91.3,
        "wind": 1.17,
        "precip": 0.048,
        "tourism_score": 7.4
      },
      "5": {
        "temp": 26.54,
        "apparent_temp": 27.96,
        "humidity": 83.8,
        "dew_point": 23.49,
        "cloud": 46.8,
        "opaque_cloud": 49.4,
        "wind": 0.94,
        "precip": 0.068,
        "tourism_score": 7.3
      },
      "6": {
        "temp": 27.35,
        "apparent_temp": 29.59,
        "humidity": 79.3,
        "dew_point": 23.35,
        "cloud": 60.3,
        "opaque_cloud": 72.3,
        "wind": 1.09,
        "precip": 0.058,
        "tourism_score": 5.6
      },
      "7": {
        "temp": 28.06,
        "apparent_temp": 31.17,
        "humidity": 76.4,
        "dew_point": 23.33,
        "cloud": 53.5,
        "opaque_cloud": 67.4,
        "wind": 1.28,
        "precip": 0.068,
        "tourism_score": 4.9
      },
      "8": {
        "temp": 28.85,
        "apparent_temp": 32.62,
        "humidity": 73.6,
        "dew_point": 23.52,
        "cloud": 54.2,
        "opaque_cloud": 54.2,
        "wind": 1.41,
        "precip": 0.074,
        "tourism_score": 5.0
      },
      "9": {
        "temp": 29.68,
        "apparent_temp": 33.88,
        "humidity": 70.1,
        "dew_point": 23.47,
        "cloud": 46.1,
        "opaque_cloud": 57.7,
        "wind": 1.61,
        "precip": 0.1,
        "tourism_score": 4.7
      },
      "10": {
        "temp": 30.52,
        "apparent_temp": 34.71,
        "humidity": 65.9,
        "dew_point": 23.17,
        "cloud": 39.4,
        "opaque_cloud": 50.3,
        "wind": 1.81,
        "precip": 0.126,
        "tourism_score": 4.6
      },
      "11": {
        "temp": 31.35,
        "apparent_temp": 35.86,
        "humidity": 62.7,
        "dew_point": 23.09,
        "cloud": 44.5,
        "opaque_cloud": 45.5,
        "wind": 2.01,
        "precip": 0.177,
        "tourism_score": 4.4
      },
      "12": {
        "temp": 32.17,
        "apparent_temp": 37.1,
        "humidity": 60.2,
        "dew_point": 23.17,
        "cloud": 53.9,
        "opaque_cloud": 41.0,
        "wind": 2.22,
        "precip": 0.287,
        "tourism_score": 4.5
      },
      "13": {
        "temp": 33.01,
        "apparent_temp": 37.85,
        "humidity": 57.1,
        "dew_point": 22.95,
        "cloud": 46.8,
        "opaque_cloud": 35.2,
        "wind": 2.41,
        "precip": 0.539,
        "tourism_score": 4.4
      },
      "14": {
        "temp": 33.84,
        "apparent_temp": 40.45,
        "humidity": 57.7,
        "dew_point": 23.88,
        "cloud": 61.0,
        "opaque_cloud": 61.0,
        "wind": 2.61,
        "precip": 0.61,
        "tourism_score": 3.6
      },
      "15": {
        "temp": 33.29,
        "apparent_temp": 38.63,
        "humidity": 57.3,
        "dew_point": 23.25,
        "cloud": 39.4,
        "opaque_cloud": 37.1,
        "wind": 2.62,
        "precip": 0.455,
        "tourism_score": 4.3
      },
      "16": {
        "temp": 32.78,
        "apparent_temp": 37.91,
        "humidity": 59.2,
        "dew_point": 23.29,
        "cloud": 39.4,
        "opaque_cloud": 39.4,
        "wind": 2.6,
        "precip": 0.432,
        "tourism_score": 4.3
      },
      "17": {
        "temp": 32.31,
        "apparent_temp": 37.15,
        "humidity": 61.1,
        "dew_point": 23.29,
        "cloud": 67.7,
        "opaque_cloud": 67.7,
        "wind": 2.62,
        "precip": 0.413,
        "tourism_score": 4.0
      },
      "18": {
        "temp": 29.27,
        "apparent_temp": 33.82,
        "humidity": 75.3,
        "dew_point": 24.32,
        "cloud": 65.5,
        "opaque_cloud": 65.5,
        "wind": 1.11,
        "precip": 0.274,
        "tourism_score": 4.6
      },
      "19": {
        "temp": 29.05,
        "apparent_temp": 33.7,
        "humidity": 77.1,
        "dew_point": 24.52,
        "cloud": 71.0,
        "opaque_cloud": 69.4,
        "wind": 1.24,
        "precip": 0.271,
        "tourism_score": 4.4
      },
      "20": {
        "temp": 28.88,
        "apparent_temp": 33.24,
        "humidity": 77.5,
        "dew_point": 24.41,
        "cloud": 68.7,
        "opaque_cloud": 69.4,
        "wind": 1.32,
        "precip": 0.316,
        "tourism_score": 4.3
      },
      "21": {
        "temp": 28.76,
        "apparent_temp": 32.99,
        "humidity": 78.1,
        "dew_point": 24.45,
        "cloud": 69.0,
        "opaque_cloud": 70.6,
        "wind": 1.31,
        "precip": 0.187,
        "tourism_score": 4.7
      },
      "22": {
        "temp": 27.81,
        "apparent_temp": 31.1,
        "humidity": 81.9,
        "dew_point": 24.35,
        "cloud": 76.1,
        "opaque_cloud": 75.8,
        "wind": 1.23,
        "precip": 0.113,
        "tourism_score": 5.2
      },
      "23": {
        "temp": 26.63,
        "apparent_temp": 28.28,
        "humidity": 86.5,
        "dew_point": 24.13,
        "cloud": 83.2,
        "opaque_cloud": 84.8,
        "wind": 1.11,
        "precip": 0.045,
        "tourism_score": 6.2
      }
    },
    "8": {
      "0": {
        "temp": 27.15,
        "apparent_temp": 29.02,
        "humidity": 76.8,
        "dew_point": 22.61,
        "cloud": 66.1,
        "opaque_cloud": 69.4,
        "wind": 1.92,
        "precip": 0.165,
        "tourism_score": 6.2
      },
      "1": {
        "temp": 26.52,
        "apparent_temp": 27.55,
        "humidity": 79.2,
        "dew_point": 22.53,
        "cloud": 67.7,
        "opaque_cloud": 73.5,
        "wind": 1.84,
        "precip": 0.11,
        "tourism_score": 7.0
      },
      "2": {
        "temp": 26.21,
        "apparent_temp": 26.83,
        "humidity": 80.9,
        "dew_point": 22.6,
        "cloud": 66.8,
        "opaque_cloud": 75.8,
        "wind": 1.74,
        "precip": 0.032,
        "tourism_score": 7.3
      },
      "3": {
        "temp": 26.15,
        "apparent_temp": 26.86,
        "humidity": 81.5,
        "dew_point": 22.68,
        "cloud": 61.0,
        "opaque_cloud": 75.2,
        "wind": 1.67,
        "precip": 0.203,
        "tourism_score": 7.3
      },
      "4": {
        "temp": 25.73,
        "apparent_temp": 26.0,
        "humidity": 83.2,
        "dew_point": 22.6,
        "cloud": 62.6,
        "opaque_cloud": 78.7,
        "wind": 1.64,
        "precip": 0.158,
        "tourism_score": 7.7
      },
      "5": {
        "temp": 26.05,
        "apparent_temp": 27.11,
        "humidity": 85.8,
        "dew_point": 23.42,
        "cloud": 37.1,
        "opaque_cloud": 37.1,
        "wind": 0.93,
        "precip": 0.103,
        "tourism_score": 7.9
      },
      "6": {
        "temp": 26.77,
        "apparent_temp": 28.42,
        "humidity": 81.6,
        "dew_point": 23.28,
        "cloud": 62.6,
        "opaque_cloud": 76.1,
        "wind": 1.21,
        "precip": 0.152,
        "tourism_score": 6.3
      },
      "7": {
        "temp": 27.4,
        "apparent_temp": 29.93,
        "humidity": 79.7,
        "dew_point": 23.51,
        "cloud": 58.4,
        "opaque_cloud": 73.2,
        "wind": 1.43,
        "precip": 0.171,
        "tourism_score": 5.8
      },
      "8": {
        "temp": 28.05,
        "apparent_temp": 31.48,
        "humidity": 77.0,
        "dew_point": 23.52,
        "cloud": 52.3,
        "opaque_cloud": 55.2,
        "wind": 1.64,
        "precip": 0.103,
        "tourism_score": 5.5
      },
      "9": {
        "temp": 28.83,
        "apparent_temp": 32.8,
        "humidity": 72.9,
        "dew_point": 23.36,
        "cloud": 51.0,
        "opaque_cloud": 63.5,
        "wind": 1.84,
        "precip": 0.119,
        "tourism_score": 4.7
      },
      "10": {
        "temp": 29.75,
        "apparent_temp": 33.08,
        "humidity": 65.0,
        "dew_point": 22.18,
        "cloud": 45.5,
        "opaque_cloud": 49.4,
        "wind": 2.0,
        "precip": 0.232,
        "tourism_score": 4.8
      },
      "11": {
        "temp": 30.51,
        "apparent_temp": 33.95,
        "humidity": 61.4,
        "dew_point": 21.92,
        "cloud": 41.3,
        "opaque_cloud": 42.6,
        "wind": 2.19,
        "precip": 0.274,
        "tourism_score": 4.8
      },
      "12": {
        "temp": 31.27,
        "apparent_temp": 35.2,
        "humidity": 59.6,
        "dew_point": 22.18,
        "cloud": 43.2,
        "opaque_cloud": 39.7,
        "wind": 2.36,
        "precip": 0.223,
        "tourism_score": 4.8
      },
      "13": {
        "temp": 32.18,
        "apparent_temp": 35.89,
        "humidity": 54.9,
        "dew_point": 21.63,
        "cloud": 39.4,
        "opaque_cloud": 32.6,
        "wind": 2.51,
        "precip": 0.103,
        "tourism_score": 5.0
      },
      "14": {
        "temp": 32.97,
        "apparent_temp": 37.1,
        "humidity": 53.5,
        "dew_point": 21.93,
        "cloud": 54.5,
        "opaque_cloud": 54.5,
        "wind": 2.68,
        "precip": 0.103,
        "tourism_score": 4.3
      },
      "15": {
        "temp": 32.74,
        "apparent_temp": 36.71,
        "humidity": 54.2,
        "dew_point": 21.94,
        "cloud": 39.4,
        "opaque_cloud": 31.0,
        "wind": 2.97,
        "precip": 0.232,
        "tourism_score": 4.7
      },
      "16": {
        "temp": 32.25,
        "apparent_temp": 36.31,
        "humidity": 56.4,
        "dew_point": 22.06,
        "cloud": 35.8,
        "opaque_cloud": 35.5,
        "wind": 3.06,
        "precip": 0.132,
        "tourism_score": 4.7
      },
      "17": {
        "temp": 31.9,
        "apparent_temp": 35.33,
        "humidity": 55.5,
        "dew_point": 21.46,
        "cloud": 57.7,
        "opaque_cloud": 57.7,
        "wind": 3.2,
        "precip": 0.168,
        "tourism_score": 4.4
      },
      "18": {
        "temp": 30.01,
        "apparent_temp": 33.51,
        "humidity": 64.6,
        "dew_point": 22.38,
        "cloud": 47.7,
        "opaque_cloud": 48.4,
        "wind": 1.88,
        "precip": 0.184,
        "tourism_score": 4.8
      },
      "19": {
        "temp": 29.75,
        "apparent_temp": 33.22,
        "humidity": 65.7,
        "dew_point": 22.37,
        "cloud": 50.6,
        "opaque_cloud": 51.0,
        "wind": 1.95,
        "precip": 0.119,
        "tourism_score": 4.9
      },
      "20": {
        "temp": 29.46,
        "apparent_temp": 32.74,
        "humidity": 66.2,
        "dew_point": 22.26,
        "cloud": 50.3,
        "opaque_cloud": 49.7,
        "wind": 1.99,
        "precip": 0.052,
        "tourism_score": 5.1
      },
      "21": {
        "temp": 29.41,
        "apparent_temp": 32.79,
        "humidity": 67.3,
        "dew_point": 22.48,
        "cloud": 54.5,
        "opaque_cloud": 52.6,
        "wind": 1.92,
        "precip": 0.035,
        "tourism_score": 5.0
      },
      "22": {
        "temp": 28.51,
        "apparent_temp": 31.14,
        "humidity": 70.8,
        "dew_point": 22.5,
        "cloud": 60.3,
        "opaque_cloud": 59.0,
        "wind": 1.97,
        "precip": 0.026,
        "tourism_score": 5.5
      },
      "23": {
        "temp": 27.27,
        "apparent_temp": 29.07,
        "humidity": 76.1,
        "dew_point": 22.55,
        "cloud": 62.3,
        "opaque_cloud": 67.4,
        "wind": 1.92,
        "precip": 0.119,
        "tourism_score": 6.2
      }
    },
    "9": {
      "0": {
        "temp": 22.64,
        "apparent_temp": 22.64,
        "humidity": 86.5,
        "dew_point": 20.25,
        "cloud": 78.7,
        "opaque_cloud": 85.3,
        "wind": 1.66,
        "precip": 0.047,
        "tourism_score": 7.7
      },
      "1": {
        "temp": 22.58,
        "apparent_temp": 22.58,
        "humidity": 87.2,
        "dew_point": 20.33,
        "cloud": 79.7,
        "opaque_cloud": 87.3,
        "wind": 1.63,
        "precip": 0.043,
        "tourism_score": 7.6
      },
      "2": {
        "temp": 22.56,
        "apparent_temp": 22.56,
        "humidity": 87.5,
        "dew_point": 20.35,
        "cloud": 83.3,
        "opaque_cloud": 86.7,
        "wind": 1.61,
        "precip": 0.07,
        "tourism_score": 7.6
      },
      "3": {
        "temp": 22.5,
        "apparent_temp": 22.5,
        "humidity": 88.0,
        "dew_point": 20.4,
        "cloud": 81.7,
        "opaque_cloud": 87.3,
        "wind": 1.61,
        "precip": 0.067,
        "tourism_score": 7.6
      },
      "4": {
        "temp": 22.51,
        "apparent_temp": 22.51,
        "humidity": 88.2,
        "dew_point": 20.45,
        "cloud": 78.0,
        "opaque_cloud": 88.0,
        "wind": 1.56,
        "precip": 0.053,
        "tourism_score": 7.6
      },
      "5": {
        "temp": 22.56,
        "apparent_temp": 22.68,
        "humidity": 89.6,
        "dew_point": 20.73,
        "cloud": 58.0,
        "opaque_cloud": 58.0,
        "wind": 2.17,
        "precip": 0.07,
        "tourism_score": 8.2
      },
      "6": {
        "temp": 22.95,
        "apparent_temp": 23.07,
        "humidity": 87.1,
        "dew_point": 20.66,
        "cloud": 75.7,
        "opaque_cloud": 86.0,
        "wind": 2.31,
        "precip": 0.083,
        "tourism_score": 7.5
      },
      "7": {
        "temp": 23.33,
        "apparent_temp": 23.69,
        "humidity": 84.8,
        "dew_point": 20.57,
        "cloud": 71.7,
        "opaque_cloud": 82.0,
        "wind": 2.44,
        "precip": 0.11,
        "tourism_score": 7.3
      },
      "8": {
        "temp": 23.88,
        "apparent_temp": 24.95,
        "humidity": 82.1,
        "dew_point": 20.58,
        "cloud": 60.3,
        "opaque_cloud": 60.0,
        "wind": 2.58,
        "precip": 0.14,
        "tourism_score": 7.3
      },
      "9": {
        "temp": 24.64,
        "apparent_temp": 26.03,
        "humidity": 78.8,
        "dew_point": 20.64,
        "cloud": 65.3,
        "opaque_cloud": 72.0,
        "wind": 2.66,
        "precip": 0.153,
        "tourism_score": 6.6
      },
      "10": {
        "temp": 25.4,
        "apparent_temp": 26.96,
        "humidity": 74.4,
        "dew_point": 20.23,
        "cloud": 59.3,
        "opaque_cloud": 64.3,
        "wind": 2.74,
        "precip": 0.147,
        "tourism_score": 6.6
      },
      "11": {
        "temp": 26.38,
        "apparent_temp": 27.75,
        "humidity": 62.7,
        "dew_point": 18.15,
        "cloud": 50.3,
        "opaque_cloud": 46.3,
        "wind": 2.82,
        "precip": 0.14,
        "tourism_score": 6.9
      },
      "12": {
        "temp": 27.38,
        "apparent_temp": 29.09,
        "humidity": 61.2,
        "dew_point": 18.74,
        "cloud": 48.0,
        "opaque_cloud": 42.7,
        "wind": 2.87,
        "precip": 0.11,
        "tourism_score": 6.7
      },
      "13": {
        "temp": 27.99,
        "apparent_temp": 30.06,
        "humidity": 60.7,
        "dew_point": 19.24,
        "cloud": 46.0,
        "opaque_cloud": 42.3,
        "wind": 2.92,
        "precip": 0.117,
        "tourism_score": 6.4
      },
      "14": {
        "temp": 28.87,
        "apparent_temp": 31.75,
        "humidity": 59.8,
        "dew_point": 19.79,
        "cloud": 66.3,
        "opaque_cloud": 66.3,
        "wind": 2.97,
        "precip": 0.117,
        "tourism_score": 5.6
      },
      "15": {
        "temp": 28.52,
        "apparent_temp": 31.06,
        "humidity": 60.9,
        "dew_point": 19.8,
        "cloud": 41.3,
        "opaque_cloud": 43.0,
        "wind": 2.83,
        "precip": 0.197,
        "tourism_score": 6.2
      },
      "16": {
        "temp": 27.95,
        "apparent_temp": 29.72,
        "humidity": 60.4,
        "dew_point": 19.01,
        "cloud": 42.3,
        "opaque_cloud": 42.0,
        "wind": 2.7,
        "precip": 0.233,
        "tourism_score": 6.4
      },
      "17": {
        "temp": 27.63,
        "apparent_temp": 29.82,
        "humidity": 65.7,
        "dew_point": 20.23,
        "cloud": 77.0,
        "opaque_cloud": 77.0,
        "wind": 2.57,
        "precip": 0.157,
        "tourism_score": 5.6
      },
      "18": {
        "temp": 25.67,
        "apparent_temp": 26.85,
        "humidity": 70.1,
        "dew_point": 19.58,
        "cloud": 58.0,
        "opaque_cloud": 57.7,
        "wind": 1.61,
        "precip": 0.117,
        "tourism_score": 6.9
      },
      "19": {
        "temp": 25.42,
        "apparent_temp": 26.48,
        "humidity": 71.7,
        "dew_point": 19.74,
        "cloud": 59.3,
        "opaque_cloud": 60.0,
        "wind": 1.62,
        "precip": 0.187,
        "tourism_score": 6.8
      },
      "20": {
        "temp": 24.97,
        "apparent_temp": 25.95,
        "humidity": 74.4,
        "dew_point": 19.92,
        "cloud": 62.7,
        "opaque_cloud": 65.0,
        "wind": 1.66,
        "precip": 0.14,
        "tourism_score": 7.0
      },
      "21": {
        "temp": 24.78,
        "apparent_temp": 25.77,
        "humidity": 76.1,
        "dew_point": 20.14,
        "cloud": 68.3,
        "opaque_cloud": 67.3,
        "wind": 1.71,
        "precip": 0.09,
        "tourism_score": 7.1
      },
      "22": {
        "temp": 24.59,
        "apparent_temp": 25.59,
        "humidity": 77.7,
        "dew_point": 20.33,
        "cloud": 70.0,
        "opaque_cloud": 69.7,
        "wind": 1.73,
        "precip": 0.06,
        "tourism_score": 7.1
      },
      "23": {
        "temp": 22.53,
        "apparent_temp": 22.53,
        "humidity": 85.5,
        "dew_point": 19.92,
        "cloud": 78.3,
        "opaque_cloud": 83.3,
        "wind": 1.73,
        "precip": 0.04,
        "tourism_score": 7.8
      }
    },
    "10": {
      "0": {
        "temp": 17.71,
        "apparent_temp": 17.62,
        "humidity": 76.5,
        "dew_point": 13.42,
        "cloud": 57.7,
        "opaque_cloud": 68.1,
        "wind": 1.98,
        "precip": 0.023,
        "tourism_score": 7.4
      },
      "1": {
        "temp": 17.1,
        "apparent_temp": 16.97,
        "humidity": 78.4,
        "dew_point": 13.22,
        "cloud": 59.0,
        "opaque_cloud": 71.9,
        "wind": 1.99,
        "precip": 0.019,
        "tourism_score": 7.2
      },
      "2": {
        "temp": 16.71,
        "apparent_temp": 16.56,
        "humidity": 80.3,
        "dew_point": 13.26,
        "cloud": 63.2,
        "opaque_cloud": 72.3,
        "wind": 2.1,
        "precip": 0.023,
        "tourism_score": 7.0
      },
      "3": {
        "temp": 16.64,
        "apparent_temp": 16.49,
        "humidity": 80.3,
        "dew_point": 13.17,
        "cloud": 66.1,
        "opaque_cloud": 74.8,
        "wind": 2.08,
        "precip": 0.013,
        "tourism_score": 7.0
      },
      "4": {
        "temp": 16.34,
        "apparent_temp": 16.2,
        "humidity": 81.8,
        "dew_point": 13.18,
        "cloud": 68.4,
        "opaque_cloud": 78.7,
        "wind": 2.08,
        "precip": 0.029,
        "tourism_score": 6.7
      },
      "5": {
        "temp": 16.89,
        "apparent_temp": 16.76,
        "humidity": 81.8,
        "dew_point": 13.62,
        "cloud": 50.6,
        "opaque_cloud": 53.5,
        "wind": 2.78,
        "precip": 0.023,
        "tourism_score": 7.4
      },
      "6": {
        "temp": 17.34,
        "apparent_temp": 17.22,
        "humidity": 78.2,
        "dew_point": 13.35,
        "cloud": 58.1,
        "opaque_cloud": 71.6,
        "wind": 2.98,
        "precip": 0.032,
        "tourism_score": 7.2
      },
      "7": {
        "temp": 17.63,
        "apparent_temp": 17.55,
        "humidity": 76.4,
        "dew_point": 13.26,
        "cloud": 58.4,
        "opaque_cloud": 69.0,
        "wind": 3.21,
        "precip": 0.058,
        "tourism_score": 7.3
      },
      "8": {
        "temp": 18.2,
        "apparent_temp": 18.09,
        "humidity": 73.3,
        "dew_point": 13.13,
        "cloud": 58.1,
        "opaque_cloud": 58.1,
        "wind": 3.42,
        "precip": 0.048,
        "tourism_score": 7.6
      },
      "9": {
        "temp": 19.27,
        "apparent_temp": 19.2,
        "humidity": 68.1,
        "dew_point": 12.98,
        "cloud": 51.0,
        "opaque_cloud": 54.5,
        "wind": 3.47,
        "precip": 0.052,
        "tourism_score": 7.9
      },
      "10": {
        "temp": 20.25,
        "apparent_temp": 20.27,
        "humidity": 61.6,
        "dew_point": 12.3,
        "cloud": 41.9,
        "opaque_cloud": 43.9,
        "wind": 3.54,
        "precip": 0.052,
        "tourism_score": 8.2
      },
      "11": {
        "temp": 21.1,
        "apparent_temp": 21.12,
        "humidity": 57.2,
        "dew_point": 11.8,
        "cloud": 37.1,
        "opaque_cloud": 36.5,
        "wind": 3.6,
        "precip": 0.042,
        "tourism_score": 8.4
      },
      "12": {
        "temp": 22.14,
        "apparent_temp": 22.15,
        "humidity": 55.2,
        "dew_point": 12.2,
        "cloud": 33.9,
        "opaque_cloud": 32.9,
        "wind": 3.65,
        "precip": 0.058,
        "tourism_score": 8.5
      },
      "13": {
        "temp": 23.15,
        "apparent_temp": 23.24,
        "humidity": 51.9,
        "dew_point": 12.13,
        "cloud": 29.0,
        "opaque_cloud": 27.4,
        "wind": 3.72,
        "precip": 0.081,
        "tourism_score": 8.4
      },
      "14": {
        "temp": 24.19,
        "apparent_temp": 24.29,
        "humidity": 48.8,
        "dew_point": 11.97,
        "cloud": 54.2,
        "opaque_cloud": 54.2,
        "wind": 3.77,
        "precip": 0.042,
        "tourism_score": 7.6
      },
      "15": {
        "temp": 24.07,
        "apparent_temp": 24.17,
        "humidity": 49.9,
        "dew_point": 12.08,
        "cloud": 30.6,
        "opaque_cloud": 24.8,
        "wind": 3.6,
        "precip": 0.048,
        "tourism_score": 8.5
      },
      "16": {
        "temp": 23.66,
        "apparent_temp": 23.83,
        "humidity": 53.1,
        "dew_point": 12.92,
        "cloud": 30.0,
        "opaque_cloud": 30.6,
        "wind": 3.35,
        "precip": 0.058,
        "tourism_score": 8.3
      },
      "17": {
        "temp": 23.52,
        "apparent_temp": 23.77,
        "humidity": 52.9,
        "dew_point": 12.69,
        "cloud": 63.5,
        "opaque_cloud": 63.5,
        "wind": 3.07,
        "precip": 0.061,
        "tourism_score": 7.5
      },
      "18": {
        "temp": 20.08,
        "apparent_temp": 20.07,
        "humidity": 64.3,
        "dew_point": 12.97,
        "cloud": 43.9,
        "opaque_cloud": 47.7,
        "wind": 2.35,
        "precip": 0.039,
        "tourism_score": 8.2
      },
      "19": {
        "temp": 19.84,
        "apparent_temp": 19.84,
        "humidity": 65.7,
        "dew_point": 13.08,
        "cloud": 46.1,
        "opaque_cloud": 50.3,
        "wind": 2.32,
        "precip": 0.061,
        "tourism_score": 8.0
      },
      "20": {
        "temp": 19.67,
        "apparent_temp": 19.67,
        "humidity": 67.0,
        "dew_point": 13.22,
        "cloud": 50.6,
        "opaque_cloud": 52.3,
        "wind": 2.21,
        "precip": 0.039,
        "tourism_score": 8.0
      },
      "21": {
        "temp": 19.53,
        "apparent_temp": 19.5,
        "humidity": 68.4,
        "dew_point": 13.4,
        "cloud": 49.4,
        "opaque_cloud": 54.2,
        "wind": 2.15,
        "precip": 0.035,
        "tourism_score": 7.9
      },
      "22": {
        "temp": 18.65,
        "apparent_temp": 18.64,
        "humidity": 71.6,
        "dew_point": 13.31,
        "cloud": 56.5,
        "opaque_cloud": 60.0,
        "wind": 2.05,
        "precip": 0.013,
        "tourism_score": 7.8
      },
      "23": {
        "temp": 17.54,
        "apparent_temp": 17.42,
        "humidity": 76.3,
        "dew_point": 13.22,
        "cloud": 57.4,
        "opaque_cloud": 68.1,
        "wind": 1.99,
        "precip": 0.013,
        "tourism_score": 7.3
      }
    },
    "11": {
      "0": {
        "temp": 12.22,
        "apparent_temp": 11.92,
        "humidity": 84.5,
        "dew_point": 9.64,
        "cloud": 60.0,
        "opaque_cloud": 82.7,
        "wind": 1.7,
        "precip": 0.07,
        "tourism_score": 4.7
      },
      "1": {
        "temp": 11.66,
        "apparent_temp": 11.38,
        "humidity": 85.4,
        "dew_point": 9.25,
        "cloud": 59.7,
        "opaque_cloud": 83.3,
        "wind": 1.64,
        "precip": 0.057,
        "tourism_score": 4.5
      },
      "2": {
        "temp": 11.66,
        "apparent_temp": 11.4,
        "humidity": 85.0,
        "dew_point": 9.18,
        "cloud": 58.0,
        "opaque_cloud": 82.7,
        "wind": 1.65,
        "precip": 0.037,
        "tourism_score": 4.5
      },
      "3": {
        "temp": 11.65,
        "apparent_temp": 11.41,
        "humidity": 84.6,
        "dew_point": 9.08,
        "cloud": 58.7,
        "opaque_cloud": 82.0,
        "wind": 1.59,
        "precip": 0.03,
        "tourism_score": 4.6
      },
      "4": {
        "temp": 11.26,
        "apparent_temp": 11.0,
        "humidity": 85.4,
        "dew_point": 8.85,
        "cloud": 56.7,
        "opaque_cloud": 83.3,
        "wind": 1.58,
        "precip": 0.047,
        "tourism_score": 4.3
      },
      "5": {
        "temp": 11.26,
        "apparent_temp": 11.0,
        "humidity": 84.0,
        "dew_point": 8.71,
        "cloud": 56.0,
        "opaque_cloud": 69.7,
        "wind": 1.51,
        "precip": 0.073,
        "tourism_score": 4.7
      },
      "6": {
        "temp": 11.35,
        "apparent_temp": 11.08,
        "humidity": 84.0,
        "dew_point": 8.82,
        "cloud": 55.0,
        "opaque_cloud": 81.7,
        "wind": 1.59,
        "precip": 0.11,
        "tourism_score": 4.4
      },
      "7": {
        "temp": 11.38,
        "apparent_temp": 11.12,
        "humidity": 83.4,
        "dew_point": 8.73,
        "cloud": 57.7,
        "opaque_cloud": 80.3,
        "wind": 1.62,
        "precip": 0.1,
        "tourism_score": 4.4
      },
      "8": {
        "temp": 11.75,
        "apparent_temp": 11.55,
        "humidity": 81.9,
        "dew_point": 8.82,
        "cloud": 54.0,
        "opaque_cloud": 62.0,
        "wind": 1.48,
        "precip": 0.067,
        "tourism_score": 5.0
      },
      "9": {
        "temp": 12.37,
        "apparent_temp": 12.17,
        "humidity": 79.3,
        "dew_point": 9.04,
        "cloud": 56.0,
        "opaque_cloud": 73.7,
        "wind": 1.55,
        "precip": 0.04,
        "tourism_score": 5.1
      },
      "10": {
        "temp": 14.18,
        "apparent_temp": 14.04,
        "humidity": 71.5,
        "dew_point": 9.04,
        "cloud": 49.3,
        "opaque_cloud": 60.3,
        "wind": 1.66,
        "precip": 0.043,
        "tourism_score": 6.2
      },
      "11": {
        "temp": 15.62,
        "apparent_temp": 15.55,
        "humidity": 66.3,
        "dew_point": 9.17,
        "cloud": 42.7,
        "opaque_cloud": 51.3,
        "wind": 1.69,
        "precip": 0.043,
        "tourism_score": 6.9
      },
      "12": {
        "temp": 16.35,
        "apparent_temp": 16.29,
        "humidity": 63.7,
        "dew_point": 9.24,
        "cloud": 40.3,
        "opaque_cloud": 47.3,
        "wind": 1.72,
        "precip": 0.047,
        "tourism_score": 7.3
      },
      "13": {
        "temp": 17.54,
        "apparent_temp": 17.46,
        "humidity": 59.7,
        "dew_point": 9.22,
        "cloud": 39.0,
        "opaque_cloud": 40.3,
        "wind": 1.78,
        "precip": 0.043,
        "tourism_score": 7.7
      },
      "14": {
        "temp": 18.29,
        "apparent_temp": 18.22,
        "humidity": 57.5,
        "dew_point": 9.37,
        "cloud": 51.3,
        "opaque_cloud": 51.0,
        "wind": 1.86,
        "precip": 0.04,
        "tourism_score": 7.5
      },
      "15": {
        "temp": 18.38,
        "apparent_temp": 18.32,
        "humidity": 57.5,
        "dew_point": 9.51,
        "cloud": 36.7,
        "opaque_cloud": 36.3,
        "wind": 2.17,
        "precip": 0.057,
        "tourism_score": 7.9
      },
      "16": {
        "temp": 17.56,
        "apparent_temp": 17.5,
        "humidity": 61.4,
        "dew_point": 9.82,
        "cloud": 43.3,
        "opaque_cloud": 43.0,
        "wind": 2.1,
        "precip": 0.04,
        "tourism_score": 7.7
      },
      "17": {
        "temp": 16.86,
        "apparent_temp": 16.8,
        "humidity": 64.6,
        "dew_point": 9.95,
        "cloud": 49.3,
        "opaque_cloud": 51.0,
        "wind": 1.94,
        "precip": 0.033,
        "tourism_score": 7.3
      },
      "18": {
        "temp": 14.31,
        "apparent_temp": 14.11,
        "humidity": 75.1,
        "dew_point": 9.89,
        "cloud": 60.3,
        "opaque_cloud": 65.7,
        "wind": 1.88,
        "precip": 0.053,
        "tourism_score": 6.1
      },
      "19": {
        "temp": 14.21,
        "apparent_temp": 13.98,
        "humidity": 75.9,
        "dew_point": 9.96,
        "cloud": 57.7,
        "opaque_cloud": 67.0,
        "wind": 1.84,
        "precip": 0.053,
        "tourism_score": 6.0
      },
      "20": {
        "temp": 14.06,
        "apparent_temp": 13.84,
        "humidity": 77.2,
        "dew_point": 10.07,
        "cloud": 58.7,
        "opaque_cloud": 68.7,
        "wind": 1.83,
        "precip": 0.037,
        "tourism_score": 5.9
      },
      "21": {
        "temp": 13.92,
        "apparent_temp": 13.65,
        "humidity": 77.7,
        "dew_point": 10.01,
        "cloud": 54.7,
        "opaque_cloud": 69.3,
        "wind": 1.79,
        "precip": 0.033,
        "tourism_score": 5.8
      },
      "22": {
        "temp": 12.96,
        "apparent_temp": 12.59,
        "humidity": 80.7,
        "dew_point": 9.66,
        "cloud": 55.0,
        "opaque_cloud": 75.3,
        "wind": 1.73,
        "precip": 0.08,
        "tourism_score": 5.2
      },
      "23": {
        "temp": 12.04,
        "apparent_temp": 11.64,
        "humidity": 84.0,
        "dew_point": 9.35,
        "cloud": 60.3,
        "opaque_cloud": 81.7,
        "wind": 1.71,
        "precip": 0.063,
        "tourism_score": 4.7
      }
    },
    "12": {
      "0": {
        "temp": 6.57,
        "apparent_temp": 6.07,
        "humidity": 84.9,
        "dew_point": 4.15,
        "cloud": 49.7,
        "opaque_cloud": 82.6,
        "wind": 1.41,
        "precip": 0.061,
        "tourism_score": 3.2
      },
      "1": {
        "temp": 5.99,
        "apparent_temp": 5.42,
        "humidity": 86.4,
        "dew_point": 3.84,
        "cloud": 53.9,
        "opaque_cloud": 84.8,
        "wind": 1.42,
        "precip": 0.068,
        "tourism_score": 3.1
      },
      "2": {
        "temp": 5.53,
        "apparent_temp": 4.93,
        "humidity": 87.7,
        "dew_point": 3.6,
        "cloud": 49.7,
        "opaque_cloud": 86.5,
        "wind": 1.38,
        "precip": 0.048,
        "tourism_score": 3.1
      },
      "3": {
        "temp": 5.52,
        "apparent_temp": 4.91,
        "humidity": 87.6,
        "dew_point": 3.6,
        "cloud": 48.4,
        "opaque_cloud": 86.5,
        "wind": 1.38,
        "precip": 0.087,
        "tourism_score": 2.9
      },
      "4": {
        "temp": 5.31,
        "apparent_temp": 4.68,
        "humidity": 88.2,
        "dew_point": 3.48,
        "cloud": 47.7,
        "opaque_cloud": 88.1,
        "wind": 1.4,
        "precip": 0.058,
        "tourism_score": 3.0
      },
      "5": {
        "temp": 4.97,
        "apparent_temp": 4.09,
        "humidity": 90.4,
        "dew_point": 3.49,
        "cloud": 47.1,
        "opaque_cloud": 64.5,
        "wind": 1.68,
        "precip": 0.042,
        "tourism_score": 3.5
      },
      "6": {
        "temp": 5.06,
        "apparent_temp": 4.12,
        "humidity": 89.7,
        "dew_point": 3.46,
        "cloud": 54.8,
        "opaque_cloud": 89.0,
        "wind": 1.77,
        "precip": 0.052,
        "tourism_score": 2.9
      },
      "7": {
        "temp": 5.09,
        "apparent_temp": 3.87,
        "humidity": 89.5,
        "dew_point": 3.53,
        "cloud": 51.9,
        "opaque_cloud": 88.4,
        "wind": 2.01,
        "precip": 0.042,
        "tourism_score": 3.0
      },
      "8": {
        "temp": 5.92,
        "apparent_temp": 4.6,
        "humidity": 90.0,
        "dew_point": 4.03,
        "cloud": 53.2,
        "opaque_cloud": 66.5,
        "wind": 2.22,
        "precip": 0.029,
        "tourism_score": 3.5
      },
      "9": {
        "temp": 6.5,
        "apparent_temp": 5.27,
        "humidity": 85.7,
        "dew_point": 4.12,
        "cloud": 54.5,
        "opaque_cloud": 82.6,
        "wind": 2.36,
        "precip": 0.029,
        "tourism_score": 3.2
      },
      "10": {
        "temp": 8.67,
        "apparent_temp": 7.69,
        "humidity": 77.8,
        "dew_point": 4.62,
        "cloud": 46.1,
        "opaque_cloud": 70.0,
        "wind": 2.42,
        "precip": 0.032,
        "tourism_score": 3.8
      },
      "11": {
        "temp": 10.97,
        "apparent_temp": 10.32,
        "humidity": 69.8,
        "dew_point": 4.89,
        "cloud": 43.9,
        "opaque_cloud": 57.1,
        "wind": 2.56,
        "precip": 0.032,
        "tourism_score": 4.8
      },
      "12": {
        "temp": 11.09,
        "apparent_temp": 10.42,
        "humidity": 67.5,
        "dew_point": 4.93,
        "cloud": 43.9,
        "opaque_cloud": 52.9,
        "wind": 2.71,
        "precip": 0.061,
        "tourism_score": 4.9
      },
      "13": {
        "temp": 12.36,
        "apparent_temp": 11.81,
        "humidity": 63.1,
        "dew_point": 4.92,
        "cloud": 36.5,
        "opaque_cloud": 46.1,
        "wind": 2.84,
        "precip": 0.048,
        "tourism_score": 5.7
      },
      "14": {
        "temp": 12.94,
        "apparent_temp": 12.39,
        "humidity": 61.1,
        "dew_point": 5.28,
        "cloud": 44.5,
        "opaque_cloud": 45.8,
        "wind": 2.88,
        "precip": 0.032,
        "tourism_score": 5.9
      },
      "15": {
        "temp": 12.8,
        "apparent_temp": 12.23,
        "humidity": 61.3,
        "dew_point": 5.06,
        "cloud": 35.2,
        "opaque_cloud": 42.3,
        "wind": 2.68,
        "precip": 0.039,
        "tourism_score": 6.0
      },
      "16": {
        "temp": 12.47,
        "apparent_temp": 11.89,
        "humidity": 64.1,
        "dew_point": 5.41,
        "cloud": 40.6,
        "opaque_cloud": 46.1,
        "wind": 2.46,
        "precip": 0.048,
        "tourism_score": 5.7
      },
      "17": {
        "temp": 12.54,
        "apparent_temp": 11.95,
        "humidity": 64.0,
        "dew_point": 5.38,
        "cloud": 43.9,
        "opaque_cloud": 45.2,
        "wind": 2.18,
        "precip": 0.061,
        "tourism_score": 5.6
      },
      "18": {
        "temp": 9.8,
        "apparent_temp": 9.39,
        "humidity": 73.9,
        "dew_point": 5.16,
        "cloud": 49.4,
        "opaque_cloud": 64.2,
        "wind": 1.57,
        "precip": 0.103,
        "tourism_score": 4.1
      },
      "19": {
        "temp": 9.43,
        "apparent_temp": 8.96,
        "humidity": 75.0,
        "dew_point": 5.19,
        "cloud": 48.7,
        "opaque_cloud": 66.8,
        "wind": 1.58,
        "precip": 0.071,
        "tourism_score": 3.9
      },
      "20": {
        "temp": 8.96,
        "apparent_temp": 8.38,
        "humidity": 77.5,
        "dew_point": 5.12,
        "cloud": 48.4,
        "opaque_cloud": 66.5,
        "wind": 1.53,
        "precip": 0.074,
        "tourism_score": 3.8
      },
      "21": {
        "temp": 8.66,
        "apparent_temp": 8.19,
        "humidity": 79.6,
        "dew_point": 5.23,
        "cloud": 51.0,
        "opaque_cloud": 73.5,
        "wind": 1.44,
        "precip": 0.065,
        "tourism_score": 3.7
      },
      "22": {
        "temp": 7.67,
        "apparent_temp": 7.11,
        "humidity": 83.1,
        "dew_point": 4.93,
        "cloud": 49.0,
        "opaque_cloud": 78.1,
        "wind": 1.43,
        "precip": 0.068,
        "tourism_score": 3.4
      },
      "23": {
        "temp": 6.76,
        "apparent_temp": 6.21,
        "humidity": 85.3,
        "dew_point": 4.43,
        "cloud": 51.9,
        "opaque_cloud": 83.9,
        "wind": 1.4,
        "precip": 0.052,
        "tourism_score": 3.2
      }
    }
  },
  "methodology": {
    "source": "OneBuilding EPW/TMYx-CSWD typical meteorological year files; Page structure and scoring thresholds are generated from local climate-processing rules, not copied raw data.",
    "temperature": "Monthly high/low use the average of daily highs/lows, matching the climate-page convention better than one-month extremes.",
    "cloud_categories": [
      [
        "clear",
        "晴天",
        0,
        20
      ],
      [
        "mostly_clear",
        "大部分晴天",
        20,
        40
      ],
      [
        "partly_cloudy",
        "部分多云",
        40,
        60
      ],
      [
        "mostly_cloudy",
        "大部分多云",
        60,
        80
      ],
      [
        "overcast",
        "阴天",
        80,
        101
      ]
    ],
    "humidity_categories": [
      [
        "dry",
        "干燥",
        -100,
        13
      ],
      [
        "comfortable",
        "舒适",
        13,
        16
      ],
      [
        "humid",
        "潮湿",
        16,
        18
      ],
      [
        "muggy",
        "闷热",
        18,
        21
      ],
      [
        "oppressive",
        "闷热难受",
        21,
        24
      ],
      [
        "miserable",
        "极为难受",
        24,
        100
      ]
    ],
    "tourism_score": {
      "analysis_hours": "08:00-21:00 local time",
      "formula": "0.50 * apparent-temperature score + 0.25 * cloud score + 0.25 * precipitation score, averaged across daytime hours by month",
      "temperature_thresholds": "Tourism: <10°C=0, 18°C=9, 24°C=10, 27°C=9, >=32°C=1; linear interpolation between thresholds.",
      "cloud_thresholds": "Clear=10, mostly clear≈9, overcast=1; linear interpolation.",
      "precip_thresholds": "No precipitation=10, trace≈9, >=1 mm/hour=0; linear interpolation."
    },
    "prefecture_city_catalog": {
      "city_list_source": "https://zh.wikipedia.org/wiki/%E4%B8%AD%E5%8D%8E%E4%BA%BA%E6%B0%91%E5%85%B1%E5%92%8C%E5%9B%BD%E5%9C%B0%E7%BA%A7%E8%A1%8C%E6%94%BF%E5%8C%BA%E5%88%97%E8%A1%A8",
      "station_source": "OneBuilding Asia index pages for China / Hong Kong / Macau",
      "admin_level": "地级市",
      "source_station_file": "CHN_JX_Shangrao.586260_TMYx.zip",
      "source_station_wmo": "586260",
      "station_match_quality": "direct",
      "catalog_type": "prefecture_level_admin_unit"
    }
  }
}